{"metadata":{},"listing":{"city":"Amsterdam","collection_ids":null,"country":"Netherlands","has_double_blind_reviews":false,"id":11913494,"instant_bookable":true,"lat":52.37363710135083,"lng":4.89870815486865,"medium_url":"https://a2.muscache.com/im/pictures/322eb5d5-f523-47e1-a82b-34ef8f58b12e.jpg?aki_policy=medium","name":"First Class Penthouse@Canal/Centre","native_currency":"EUR","picture_url":"https://a2.muscache.com/im/pictures/322eb5d5-f523-47e1-a82b-34ef8f58b12e.jpg?aki_policy=large","price":197,"price_formatted":"€175","price_native":175,"smart_location":"Amsterdam, Netherlands","thumbnail_url":"https://a2.muscache.com/im/pictures/322eb5d5-f523-47e1-a82b-34ef8f58b12e.jpg?aki_policy=small","user":{"user":{"about":"Hi, we are Douwe and Niki, how are you doing?\r\n\r\nTogether, with many other enthousiast young people from Amsterdam, we are KeyOkay, a company specialized in shortstay renting out apartments in  Amsterdam, Antwerp and starting spring 2016 even in Florence!\r\n\r\nWhat we do\r\nEverything we do, we believe to bring people authentic value and story telling together!& We manage properties with the care and dedication (so with a high service/quality level and a personal touch) you deserves !!\r\n\r\n By taking over everything involved, like handing over keys, cleaning the apartment or providing clean sheets, we can provide our customers a safe and convenient feeling when there are abroad on one of their many journeys. For their guests we provide the extra service a reception brings to a hotel. So we are, if nescessary, available 24/7. \r\n\r\nHope to meet you soon!\r\n\r\nKeyOkay. Your house, our care.","first_name":"Douwe&Niki","has_profile_pic":true,"id":6999042,"identity_verified":true,"is_superhost":false,"picture_url":"https://a2.muscache.com/im/users/6999042/profile_pic/1419428703/original.jpg?aki_policy=profile_x_medium","reviewee_count":1477,"thumbnail_url":"https://a2.muscache.com/im/users/6999042/profile_pic/1419428703/original.jpg?aki_policy=profile_small"}},"user_id":6999042,"xl_picture_url":"https://a2.muscache.com/im/pictures/322eb5d5-f523-47e1-a82b-34ef8f58b12e.jpg?aki_policy=x_large","address":"Oudezijds Voorburgwal, Amsterdam, Noord-Holland 1012 EH, Netherlands","bathrooms":2.5,"bedrooms":3,"beds":3,"cancellation_policy":"strict","country_code":"NL","has_availability":true,"hosts":[{"about":"Hi, we are Douwe and Niki, how are you doing?\r\n\r\nTogether, with many other enthousiast young people from Amsterdam, we are KeyOkay, a company specialized in shortstay renting out apartments in  Amsterdam, Antwerp and starting spring 2016 even in Florence!\r\n\r\nWhat we do\r\nEverything we do, we believe to bring people authentic value and story telling together!& We manage properties with the care and dedication (so with a high service/quality level and a personal touch) you deserves !!\r\n\r\n By taking over everything involved, like handing over keys, cleaning the apartment or providing clean sheets, we can provide our customers a safe and convenient feeling when there are abroad on one of their many journeys. For their guests we provide the extra service a reception brings to a hotel. So we are, if nescessary, available 24/7. \r\n\r\nHope to meet you soon!\r\n\r\nKeyOkay. Your house, our care.","first_name":"Douwe&Niki","has_profile_pic":true,"id":6999042,"identity_verified":true,"is_superhost":false,"picture_url":"https://a2.muscache.com/im/users/6999042/profile_pic/1419428703/original.jpg?aki_policy=profile_x_medium","reviewee_count":1477,"thumbnail_url":"https://a2.muscache.com/im/users/6999042/profile_pic/1419428703/original.jpg?aki_policy=profile_small"}],"listing_native_currency":"EUR","market":"Amsterdam","min_nights":3,"neighborhood":"De Wallen","person_capacity":4,"picture_count":28,"picture_urls":["https://a2.muscache.com/im/pictures/322eb5d5-f523-47e1-a82b-34ef8f58b12e.jpg?aki_policy=large","https://a2.muscache.com/im/pictures/bcb652ba-3508-4af4-9ab0-8d9b4e5c1505.jpg?aki_policy=large","https://a2.muscache.com/im/pictures/71680ea5-1d84-48f8-bdd9-e90b9090f746.jpg?aki_policy=large","https://a2.muscache.com/im/pictures/935ebaff-a09c-4a42-bb6e-b400c80ac9e2.jpg?aki_policy=large","https://a2.muscache.com/im/pictures/48f8ecb3-8aba-4c59-92fb-65c1e501594d.jpg?aki_policy=large","https://a2.muscache.com/im/pictures/cb6a8cce-2c90-4e94-8f9b-9a81d7145f78.jpg?aki_policy=large","https://a2.muscache.com/im/pictures/4e1c9e76-c83f-440a-b14c-775b9859b869.jpg?aki_policy=large","https://a2.muscache.com/im/pictures/f15ee90c-5185-4d77-85ed-3d6dfadd1427.jpg?aki_policy=large","https://a2.muscache.com/im/pictures/88769bc9-da72-4ae9-8dc7-e2933288025c.jpg?aki_policy=large","https://a2.muscache.com/im/pictures/015dbac6-5436-46a4-9d84-530b277433dc.jpg?aki_policy=large","https://a2.muscache.com/im/pictures/7efd8ee8-ab1c-4ead-8a08-57b615bff4d5.jpg?aki_policy=large","https://a2.muscache.com/im/pictures/c804d528-fedf-421f-9e5c-5ccfb7c52246.jpg?aki_policy=large","https://a2.muscache.com/im/pictures/5a28062f-ed24-44fa-ab41-e91203e7a3e2.jpg?aki_policy=large","https://a2.muscache.com/im/pictures/d7a80174-f8cb-4ba1-aefc-c5f22ad6e9fa.jpg?aki_policy=large","https://a2.muscache.com/im/pictures/dd785b8b-36a1-44ea-bec4-f352db62f3a4.jpg?aki_policy=large","https://a2.muscache.com/im/pictures/f0403dc8-9adb-4b90-9ed1-d112f4d622a8.jpg?aki_policy=large","https://a2.muscache.com/im/pictures/5e5b85a1-077c-4b6e-adec-6803eac219dc.jpg?aki_policy=large","https://a2.muscache.com/im/pictures/66ce33e1-b477-4ed7-aca7-f3228028bd7e.jpg?aki_policy=large","https://a2.muscache.com/im/pictures/b2245e3b-9c0e-4934-8519-f7e5b9568e3f.jpg?aki_policy=large","https://a2.muscache.com/im/pictures/962b11f1-375d-4eb5-ab2d-72aa2635a504.jpg?aki_policy=large","https://a2.muscache.com/im/pictures/cbeace76-14cf-4614-a94d-4b7da894d95b.jpg?aki_policy=large","https://a2.muscache.com/im/pictures/9b798a60-e0e9-4544-98d5-f3312c3e676e.jpg?aki_policy=large","https://a2.muscache.com/im/pictures/4587993e-bfc5-4148-8778-40e399ea965e.jpg?aki_policy=large","https://a2.muscache.com/im/pictures/44e1dc27-91b2-4357-80cc-01c451fc5bca.jpg?aki_policy=large","https://a2.muscache.com/im/pictures/05bc28f9-3304-4bae-9b67-77d0931f67e4.jpg?aki_policy=large","https://a2.muscache.com/im/pictures/7ec2eed8-aca9-4815-b702-1f6c0dd9f13d.jpg?aki_policy=large","https://a2.muscache.com/im/pictures/04937866-5885-4bf9-a025-2ba0be69bb48.jpg?aki_policy=large","https://a2.muscache.com/im/pictures/9061d985-293d-433f-9ac2-960d4a7051b9.jpg?aki_policy=large"],"primary_host":{"about":"Hi, we are Douwe and Niki, how are you doing?\r\n\r\nTogether, with many other enthousiast young people from Amsterdam, we are KeyOkay, a company specialized in shortstay renting out apartments in  Amsterdam, Antwerp and starting spring 2016 even in Florence!\r\n\r\nWhat we do\r\nEverything we do, we believe to bring people authentic value and story telling together!& We manage properties with the care and dedication (so with a high service/quality level and a personal touch) you deserves !!\r\n\r\n By taking over everything involved, like handing over keys, cleaning the apartment or providing clean sheets, we can provide our customers a safe and convenient feeling when there are abroad on one of their many journeys. For their guests we provide the extra service a reception brings to a hotel. So we are, if nescessary, available 24/7. \r\n\r\nHope to meet you soon!\r\n\r\nKeyOkay. Your house, our care.","first_name":"Douwe&Niki","has_profile_pic":true,"id":6999042,"identity_verified":true,"is_superhost":false,"picture_url":"https://a2.muscache.com/im/users/6999042/profile_pic/1419428703/original.jpg?aki_policy=profile_x_medium","reviewee_count":1477,"thumbnail_url":"https://a2.muscache.com/im/users/6999042/profile_pic/1419428703/original.jpg?aki_policy=profile_small"},"property_type":"Apartment","reviews_count":0,"room_type":"Entire home/apt","room_type_category":"entire_home","special_offer":null,"state":"Noord-Holland","thumbnail_urls":["https://a2.muscache.com/im/pictures/322eb5d5-f523-47e1-a82b-34ef8f58b12e.jpg?aki_policy=small","https://a2.muscache.com/im/pictures/bcb652ba-3508-4af4-9ab0-8d9b4e5c1505.jpg?aki_policy=small","https://a2.muscache.com/im/pictures/71680ea5-1d84-48f8-bdd9-e90b9090f746.jpg?aki_policy=small","https://a2.muscache.com/im/pictures/935ebaff-a09c-4a42-bb6e-b400c80ac9e2.jpg?aki_policy=small","https://a2.muscache.com/im/pictures/48f8ecb3-8aba-4c59-92fb-65c1e501594d.jpg?aki_policy=small","https://a2.muscache.com/im/pictures/cb6a8cce-2c90-4e94-8f9b-9a81d7145f78.jpg?aki_policy=small","https://a2.muscache.com/im/pictures/4e1c9e76-c83f-440a-b14c-775b9859b869.jpg?aki_policy=small","https://a2.muscache.com/im/pictures/f15ee90c-5185-4d77-85ed-3d6dfadd1427.jpg?aki_policy=small","https://a2.muscache.com/im/pictures/88769bc9-da72-4ae9-8dc7-e2933288025c.jpg?aki_policy=small","https://a2.muscache.com/im/pictures/015dbac6-5436-46a4-9d84-530b277433dc.jpg?aki_policy=small","https://a2.muscache.com/im/pictures/7efd8ee8-ab1c-4ead-8a08-57b615bff4d5.jpg?aki_policy=small","https://a2.muscache.com/im/pictures/c804d528-fedf-421f-9e5c-5ccfb7c52246.jpg?aki_policy=small","https://a2.muscache.com/im/pictures/5a28062f-ed24-44fa-ab41-e91203e7a3e2.jpg?aki_policy=small","https://a2.muscache.com/im/pictures/d7a80174-f8cb-4ba1-aefc-c5f22ad6e9fa.jpg?aki_policy=small","https://a2.muscache.com/im/pictures/dd785b8b-36a1-44ea-bec4-f352db62f3a4.jpg?aki_policy=small","https://a2.muscache.com/im/pictures/f0403dc8-9adb-4b90-9ed1-d112f4d622a8.jpg?aki_policy=small","https://a2.muscache.com/im/pictures/5e5b85a1-077c-4b6e-adec-6803eac219dc.jpg?aki_policy=small","https://a2.muscache.com/im/pictures/66ce33e1-b477-4ed7-aca7-f3228028bd7e.jpg?aki_policy=small","https://a2.muscache.com/im/pictures/b2245e3b-9c0e-4934-8519-f7e5b9568e3f.jpg?aki_policy=small","https://a2.muscache.com/im/pictures/962b11f1-375d-4eb5-ab2d-72aa2635a504.jpg?aki_policy=small","https://a2.muscache.com/im/pictures/cbeace76-14cf-4614-a94d-4b7da894d95b.jpg?aki_policy=small","https://a2.muscache.com/im/pictures/9b798a60-e0e9-4544-98d5-f3312c3e676e.jpg?aki_policy=small","https://a2.muscache.com/im/pictures/4587993e-bfc5-4148-8778-40e399ea965e.jpg?aki_policy=small","https://a2.muscache.com/im/pictures/44e1dc27-91b2-4357-80cc-01c451fc5bca.jpg?aki_policy=small","https://a2.muscache.com/im/pictures/05bc28f9-3304-4bae-9b67-77d0931f67e4.jpg?aki_policy=small","https://a2.muscache.com/im/pictures/7ec2eed8-aca9-4815-b702-1f6c0dd9f13d.jpg?aki_policy=small","https://a2.muscache.com/im/pictures/04937866-5885-4bf9-a025-2ba0be69bb48.jpg?aki_policy=small","https://a2.muscache.com/im/pictures/9061d985-293d-433f-9ac2-960d4a7051b9.jpg?aki_policy=small"],"xl_picture_urls":["https://a2.muscache.com/im/pictures/322eb5d5-f523-47e1-a82b-34ef8f58b12e.jpg?aki_policy=x_large","https://a2.muscache.com/im/pictures/bcb652ba-3508-4af4-9ab0-8d9b4e5c1505.jpg?aki_policy=x_large","https://a2.muscache.com/im/pictures/71680ea5-1d84-48f8-bdd9-e90b9090f746.jpg?aki_policy=x_large","https://a2.muscache.com/im/pictures/935ebaff-a09c-4a42-bb6e-b400c80ac9e2.jpg?aki_policy=x_large","https://a2.muscache.com/im/pictures/48f8ecb3-8aba-4c59-92fb-65c1e501594d.jpg?aki_policy=x_large","https://a2.muscache.com/im/pictures/cb6a8cce-2c90-4e94-8f9b-9a81d7145f78.jpg?aki_policy=x_large","https://a2.muscache.com/im/pictures/4e1c9e76-c83f-440a-b14c-775b9859b869.jpg?aki_policy=x_large","https://a2.muscache.com/im/pictures/f15ee90c-5185-4d77-85ed-3d6dfadd1427.jpg?aki_policy=x_large","https://a2.muscache.com/im/pictures/88769bc9-da72-4ae9-8dc7-e2933288025c.jpg?aki_policy=x_large","https://a2.muscache.com/im/pictures/015dbac6-5436-46a4-9d84-530b277433dc.jpg?aki_policy=x_large","https://a2.muscache.com/im/pictures/7efd8ee8-ab1c-4ead-8a08-57b615bff4d5.jpg?aki_policy=x_large","https://a2.muscache.com/im/pictures/c804d528-fedf-421f-9e5c-5ccfb7c52246.jpg?aki_policy=x_large","https://a2.muscache.com/im/pictures/5a28062f-ed24-44fa-ab41-e91203e7a3e2.jpg?aki_policy=x_large","https://a2.muscache.com/im/pictures/d7a80174-f8cb-4ba1-aefc-c5f22ad6e9fa.jpg?aki_policy=x_large","https://a2.muscache.com/im/pictures/dd785b8b-36a1-44ea-bec4-f352db62f3a4.jpg?aki_policy=x_large","https://a2.muscache.com/im/pictures/f0403dc8-9adb-4b90-9ed1-d112f4d622a8.jpg?aki_policy=x_large","https://a2.muscache.com/im/pictures/5e5b85a1-077c-4b6e-adec-6803eac219dc.jpg?aki_policy=x_large","https://a2.muscache.com/im/pictures/66ce33e1-b477-4ed7-aca7-f3228028bd7e.jpg?aki_policy=x_large","https://a2.muscache.com/im/pictures/b2245e3b-9c0e-4934-8519-f7e5b9568e3f.jpg?aki_policy=x_large","https://a2.muscache.com/im/pictures/962b11f1-375d-4eb5-ab2d-72aa2635a504.jpg?aki_policy=x_large","https://a2.muscache.com/im/pictures/cbeace76-14cf-4614-a94d-4b7da894d95b.jpg?aki_policy=x_large","https://a2.muscache.com/im/pictures/9b798a60-e0e9-4544-98d5-f3312c3e676e.jpg?aki_policy=x_large","https://a2.muscache.com/im/pictures/4587993e-bfc5-4148-8778-40e399ea965e.jpg?aki_policy=x_large","https://a2.muscache.com/im/pictures/44e1dc27-91b2-4357-80cc-01c451fc5bca.jpg?aki_policy=x_large","https://a2.muscache.com/im/pictures/05bc28f9-3304-4bae-9b67-77d0931f67e4.jpg?aki_policy=x_large","https://a2.muscache.com/im/pictures/7ec2eed8-aca9-4815-b702-1f6c0dd9f13d.jpg?aki_policy=x_large","https://a2.muscache.com/im/pictures/04937866-5885-4bf9-a025-2ba0be69bb48.jpg?aki_policy=x_large","https://a2.muscache.com/im/pictures/9061d985-293d-433f-9ac2-960d4a7051b9.jpg?aki_policy=x_large"],"zipcode":"1012 EH","bed_type":"Real Bed","bed_type_category":"real_bed","currency_symbol_left":"&euro;","force_mobile_legal_modal":true,"require_guest_profile_picture":false,"access":"","amenities":["TV","Cable TV","Internet","Wireless Internet","Kitchen","Smoking Allowed","Buzzer/Wireless Intercom","Heating","Smoke Detector","Carbon Monoxide Detector","First Aid Kit","Safety Card","Fire Extinguisher","Essentials","Shampoo","24-Hour Check-in","Hangers","Hair Dryer","Iron","Laptop Friendly Workspace","translation missing: en.hosting_amenity_49","translation missing: en.hosting_amenity_50"],"amenities_ids":[1,2,3,4,8,11,28,30,35,36,37,38,39,40,41,43,44,45,46,47,49,50],"calendar_updated_at":"today","cancel_policy":5,"cancel_policy_short_str":"Strict","check_in_time":15,"check_in_time_end":"NOT_SELECTED","check_in_time_ends_at":null,"check_in_time_start":"15","check_out_time":11,"cleaning_fee_native":50,"currency_symbol_right":null,"description":"Ever wanted to stay in Huge Penthouse in the Centre of Amsterdam at the canal?  This Penthouse is situated in the heart of Amsterdam near DAM square, Main station, Red Light district and close to Rembrandt square& the Nine Streets area.\n\nThis district is thé place to be if you are in Amsterdam. The stunning Penthouse is amazing, centrally located, spacious and part of a monumental building. It’s an house of 150 square meters with 3 different levels and located in the heart of Amsterdam at the canal. If you would like to feel and live like a local of Amsterdam this is an amazing place to stay! The ultimate Amsterdam Experience. EVERYTHING WITHIN WALKING DISTANCE!\n\nStaying at this house will undoubtedly be a marvelous experience! This house is an amazing a true distinctive experience in the heart of Amsterdam. It’s an ideal loft on a perfect central location for yourself, family and friends to start to feel like a Local of Amsterdam at the same time, with an authentic and cultural atmosphere. This neighbourhood is brimming with great cafés, culinair restaurants, bars, galleries, museums, art&design, authentic shops. All that you need is there!\n\nBecause of the wonderful location of the apartment, you can really taste how it feels to live like a local of Amsterdam in the centre of the city. \n\nThis Traditional and Authentic Penthouse has got a huge characteristic living room where you can really relax after a day of exploring the city. There is a huge flat screen TV, some comfortable couches and chairs. On the other side of the apartment there is a fully equipped open kitchen with a lovely dining table and a breakfast bar. Perfect for a lovely dinner, breakfast, lunch or some wines and beers☺\nFrom the living you have an amazing view of oldest city centre of Amsterdam and it’s a great view spot for the canal. \n\nOn the top level of the penthouse\n‘The Eagle nest’, a very spacious Masterbedroom with a Kingsize Double bed, Flatscreen TV and enough storage space with next to it a big ensuite Masterbathroom and a separate toilet. \n\nOn the third floor; You will find 2 guestrooms with both double beds and enough storage space. Next to this rooms is also a separate study room/reading room with a desk, perfect for business or work. And a guest bathroom with a Rainshower and toilet.\n\nYou will also have access to free Wifi and enough storage space. Towels and linen are included for the whole period.\nAll of this in combination with the traditional house gives you a real experience of the historical ambiance of the Amsterdam! This house is perfect for a city trip, holiday or business trip you will never forget!\n\nWe are really looking forward to meet you, show you around at the apartment and to give you all the inside tips and tricks about Amsterdam. Please notice after 8pm we ask a late arrival fee of 20 euro and after 11pm 30 euro. \n\nIf you have got any questions please contact us!","description_locale":"en","experiences_offered":"none","extra_user_info":null,"extras_price_native":50,"guests_included":2,"has_agreed_to_legal_terms":true,"has_license":false,"has_viewed_cleaning":null,"has_viewed_ib_perf_dashboard_panel":null,"has_viewed_terms":true,"house_rules":"YOU HAVE TO RESPECT THE NEIGHBOURS AND NEIGHBOURHOOD\nPLEASE TAKE CARE OF THE BELONGINGS!\nNO PARTIES","instant_book_welcome_message":"","interaction":"","is_location_exact":true,"jurisdiction_names":"Amsterdam","jurisdiction_rollout_names":"Amsterdam","language":"nl","license":null,"listing_cleaning_fee_native":50,"listing_monthly_price_native":null,"listing_price_for_extra_person_native":50,"listing_security_deposit_native":500,"listing_weekend_price_native":199,"listing_weekly_price_native":null,"locale":"nl","map_image_url":"https://maps.googleapis.com/maps/api/staticmap?maptype=roadmap&markers=52.37363710135083%2C4.89870815486865&size=480x320&zoom=15&client=gme-airbnbinc&channel=monorail-prod&signature=gvGcMf5EXFjppKnnr5OOw8UqFVw%3D","max_nights":1125,"max_nights_input_value":null,"min_nights_input_value":3,"monthly_price_factor":null,"monthly_price_native":null,"neighborhood_overview":"","notes":"","photos":[{"id":154310742,"picture":"https://a2.muscache.com/im/pictures/322eb5d5-f523-47e1-a82b-34ef8f58b12e.jpg?aki_policy=large","sort_order":1,"caption":"","large":"https://a2.muscache.com/im/pictures/322eb5d5-f523-47e1-a82b-34ef8f58b12e.jpg?aki_policy=large","large_cover":"https://a2.muscache.com/ac/pictures/322eb5d5-f523-47e1-a82b-34ef8f58b12e.jpg?interpolation=lanczos-none&size=large_cover&output-format=jpg&output-quality=70","medium":"https://a2.muscache.com/im/pictures/322eb5d5-f523-47e1-a82b-34ef8f58b12e.jpg?aki_policy=medium","mini_square":"https://a2.muscache.com/im/pictures/322eb5d5-f523-47e1-a82b-34ef8f58b12e.jpg?aki_policy=mini_square","small":"https://a2.muscache.com/im/pictures/322eb5d5-f523-47e1-a82b-34ef8f58b12e.jpg?aki_policy=small","thumbnail":"https://a2.muscache.com/im/pictures/322eb5d5-f523-47e1-a82b-34ef8f58b12e.jpg?aki_policy=small","x_large":"https://a2.muscache.com/im/pictures/322eb5d5-f523-47e1-a82b-34ef8f58b12e.jpg?aki_policy=x_large","x_large_cover":"https://a2.muscache.com/ac/pictures/322eb5d5-f523-47e1-a82b-34ef8f58b12e.jpg?interpolation=lanczos-none&size=x_large_cover&output-format=jpg&output-quality=70","x_medium":"https://a2.muscache.com/im/pictures/322eb5d5-f523-47e1-a82b-34ef8f58b12e.jpg?aki_policy=x_medium","x_small":"https://a2.muscache.com/im/pictures/322eb5d5-f523-47e1-a82b-34ef8f58b12e.jpg?aki_policy=x_small","xl_picture":"https://a2.muscache.com/im/pictures/322eb5d5-f523-47e1-a82b-34ef8f58b12e.jpg?aki_policy=x_large","xx_large":"https://a2.muscache.com/im/pictures/322eb5d5-f523-47e1-a82b-34ef8f58b12e.jpg?aki_policy=xx_large"},{"id":154310754,"picture":"https://a2.muscache.com/im/pictures/bcb652ba-3508-4af4-9ab0-8d9b4e5c1505.jpg?aki_policy=large","sort_order":2,"caption":"","large":"https://a2.muscache.com/im/pictures/bcb652ba-3508-4af4-9ab0-8d9b4e5c1505.jpg?aki_policy=large","large_cover":"https://a2.muscache.com/ac/pictures/bcb652ba-3508-4af4-9ab0-8d9b4e5c1505.jpg?interpolation=lanczos-none&size=large_cover&output-format=jpg&output-quality=70","medium":"https://a2.muscache.com/im/pictures/bcb652ba-3508-4af4-9ab0-8d9b4e5c1505.jpg?aki_policy=medium","mini_square":"https://a2.muscache.com/im/pictures/bcb652ba-3508-4af4-9ab0-8d9b4e5c1505.jpg?aki_policy=mini_square","small":"https://a2.muscache.com/im/pictures/bcb652ba-3508-4af4-9ab0-8d9b4e5c1505.jpg?aki_policy=small","thumbnail":"https://a2.muscache.com/im/pictures/bcb652ba-3508-4af4-9ab0-8d9b4e5c1505.jpg?aki_policy=small","x_large":"https://a2.muscache.com/im/pictures/bcb652ba-3508-4af4-9ab0-8d9b4e5c1505.jpg?aki_policy=x_large","x_large_cover":"https://a2.muscache.com/ac/pictures/bcb652ba-3508-4af4-9ab0-8d9b4e5c1505.jpg?interpolation=lanczos-none&size=x_large_cover&output-format=jpg&output-quality=70","x_medium":"https://a2.muscache.com/im/pictures/bcb652ba-3508-4af4-9ab0-8d9b4e5c1505.jpg?aki_policy=x_medium","x_small":"https://a2.muscache.com/im/pictures/bcb652ba-3508-4af4-9ab0-8d9b4e5c1505.jpg?aki_policy=x_small","xl_picture":"https://a2.muscache.com/im/pictures/bcb652ba-3508-4af4-9ab0-8d9b4e5c1505.jpg?aki_policy=x_large","xx_large":"https://a2.muscache.com/im/pictures/bcb652ba-3508-4af4-9ab0-8d9b4e5c1505.jpg?aki_policy=xx_large"},{"id":154310786,"picture":"https://a2.muscache.com/im/pictures/71680ea5-1d84-48f8-bdd9-e90b9090f746.jpg?aki_policy=large","sort_order":3,"caption":"","large":"https://a2.muscache.com/im/pictures/71680ea5-1d84-48f8-bdd9-e90b9090f746.jpg?aki_policy=large","large_cover":"https://a2.muscache.com/ac/pictures/71680ea5-1d84-48f8-bdd9-e90b9090f746.jpg?interpolation=lanczos-none&size=large_cover&output-format=jpg&output-quality=70","medium":"https://a2.muscache.com/im/pictures/71680ea5-1d84-48f8-bdd9-e90b9090f746.jpg?aki_policy=medium","mini_square":"https://a2.muscache.com/im/pictures/71680ea5-1d84-48f8-bdd9-e90b9090f746.jpg?aki_policy=mini_square","small":"https://a2.muscache.com/im/pictures/71680ea5-1d84-48f8-bdd9-e90b9090f746.jpg?aki_policy=small","thumbnail":"https://a2.muscache.com/im/pictures/71680ea5-1d84-48f8-bdd9-e90b9090f746.jpg?aki_policy=small","x_large":"https://a2.muscache.com/im/pictures/71680ea5-1d84-48f8-bdd9-e90b9090f746.jpg?aki_policy=x_large","x_large_cover":"https://a2.muscache.com/ac/pictures/71680ea5-1d84-48f8-bdd9-e90b9090f746.jpg?interpolation=lanczos-none&size=x_large_cover&output-format=jpg&output-quality=70","x_medium":"https://a2.muscache.com/im/pictures/71680ea5-1d84-48f8-bdd9-e90b9090f746.jpg?aki_policy=x_medium","x_small":"https://a2.muscache.com/im/pictures/71680ea5-1d84-48f8-bdd9-e90b9090f746.jpg?aki_policy=x_small","xl_picture":"https://a2.muscache.com/im/pictures/71680ea5-1d84-48f8-bdd9-e90b9090f746.jpg?aki_policy=x_large","xx_large":"https://a2.muscache.com/im/pictures/71680ea5-1d84-48f8-bdd9-e90b9090f746.jpg?aki_policy=xx_large"},{"id":154310807,"picture":"https://a2.muscache.com/im/pictures/935ebaff-a09c-4a42-bb6e-b400c80ac9e2.jpg?aki_policy=large","sort_order":4,"caption":"","large":"https://a2.muscache.com/im/pictures/935ebaff-a09c-4a42-bb6e-b400c80ac9e2.jpg?aki_policy=large","large_cover":"https://a2.muscache.com/ac/pictures/935ebaff-a09c-4a42-bb6e-b400c80ac9e2.jpg?interpolation=lanczos-none&size=large_cover&output-format=jpg&output-quality=70","medium":"https://a2.muscache.com/im/pictures/935ebaff-a09c-4a42-bb6e-b400c80ac9e2.jpg?aki_policy=medium","mini_square":"https://a2.muscache.com/im/pictures/935ebaff-a09c-4a42-bb6e-b400c80ac9e2.jpg?aki_policy=mini_square","small":"https://a2.muscache.com/im/pictures/935ebaff-a09c-4a42-bb6e-b400c80ac9e2.jpg?aki_policy=small","thumbnail":"https://a2.muscache.com/im/pictures/935ebaff-a09c-4a42-bb6e-b400c80ac9e2.jpg?aki_policy=small","x_large":"https://a2.muscache.com/im/pictures/935ebaff-a09c-4a42-bb6e-b400c80ac9e2.jpg?aki_policy=x_large","x_large_cover":"https://a2.muscache.com/ac/pictures/935ebaff-a09c-4a42-bb6e-b400c80ac9e2.jpg?interpolation=lanczos-none&size=x_large_cover&output-format=jpg&output-quality=70","x_medium":"https://a2.muscache.com/im/pictures/935ebaff-a09c-4a42-bb6e-b400c80ac9e2.jpg?aki_policy=x_medium","x_small":"https://a2.muscache.com/im/pictures/935ebaff-a09c-4a42-bb6e-b400c80ac9e2.jpg?aki_policy=x_small","xl_picture":"https://a2.muscache.com/im/pictures/935ebaff-a09c-4a42-bb6e-b400c80ac9e2.jpg?aki_policy=x_large","xx_large":"https://a2.muscache.com/im/pictures/935ebaff-a09c-4a42-bb6e-b400c80ac9e2.jpg?aki_policy=xx_large"},{"id":154310841,"picture":"https://a2.muscache.com/im/pictures/48f8ecb3-8aba-4c59-92fb-65c1e501594d.jpg?aki_policy=large","sort_order":5,"caption":"","large":"https://a2.muscache.com/im/pictures/48f8ecb3-8aba-4c59-92fb-65c1e501594d.jpg?aki_policy=large","large_cover":"https://a2.muscache.com/ac/pictures/48f8ecb3-8aba-4c59-92fb-65c1e501594d.jpg?interpolation=lanczos-none&size=large_cover&output-format=jpg&output-quality=70","medium":"https://a2.muscache.com/im/pictures/48f8ecb3-8aba-4c59-92fb-65c1e501594d.jpg?aki_policy=medium","mini_square":"https://a2.muscache.com/im/pictures/48f8ecb3-8aba-4c59-92fb-65c1e501594d.jpg?aki_policy=mini_square","small":"https://a2.muscache.com/im/pictures/48f8ecb3-8aba-4c59-92fb-65c1e501594d.jpg?aki_policy=small","thumbnail":"https://a2.muscache.com/im/pictures/48f8ecb3-8aba-4c59-92fb-65c1e501594d.jpg?aki_policy=small","x_large":"https://a2.muscache.com/im/pictures/48f8ecb3-8aba-4c59-92fb-65c1e501594d.jpg?aki_policy=x_large","x_large_cover":"https://a2.muscache.com/ac/pictures/48f8ecb3-8aba-4c59-92fb-65c1e501594d.jpg?interpolation=lanczos-none&size=x_large_cover&output-format=jpg&output-quality=70","x_medium":"https://a2.muscache.com/im/pictures/48f8ecb3-8aba-4c59-92fb-65c1e501594d.jpg?aki_policy=x_medium","x_small":"https://a2.muscache.com/im/pictures/48f8ecb3-8aba-4c59-92fb-65c1e501594d.jpg?aki_policy=x_small","xl_picture":"https://a2.muscache.com/im/pictures/48f8ecb3-8aba-4c59-92fb-65c1e501594d.jpg?aki_policy=x_large","xx_large":"https://a2.muscache.com/im/pictures/48f8ecb3-8aba-4c59-92fb-65c1e501594d.jpg?aki_policy=xx_large"},{"id":154310897,"picture":"https://a2.muscache.com/im/pictures/cb6a8cce-2c90-4e94-8f9b-9a81d7145f78.jpg?aki_policy=large","sort_order":6,"caption":"","large":"https://a2.muscache.com/im/pictures/cb6a8cce-2c90-4e94-8f9b-9a81d7145f78.jpg?aki_policy=large","large_cover":"https://a2.muscache.com/ac/pictures/cb6a8cce-2c90-4e94-8f9b-9a81d7145f78.jpg?interpolation=lanczos-none&size=large_cover&output-format=jpg&output-quality=70","medium":"https://a2.muscache.com/im/pictures/cb6a8cce-2c90-4e94-8f9b-9a81d7145f78.jpg?aki_policy=medium","mini_square":"https://a2.muscache.com/im/pictures/cb6a8cce-2c90-4e94-8f9b-9a81d7145f78.jpg?aki_policy=mini_square","small":"https://a2.muscache.com/im/pictures/cb6a8cce-2c90-4e94-8f9b-9a81d7145f78.jpg?aki_policy=small","thumbnail":"https://a2.muscache.com/im/pictures/cb6a8cce-2c90-4e94-8f9b-9a81d7145f78.jpg?aki_policy=small","x_large":"https://a2.muscache.com/im/pictures/cb6a8cce-2c90-4e94-8f9b-9a81d7145f78.jpg?aki_policy=x_large","x_large_cover":"https://a2.muscache.com/ac/pictures/cb6a8cce-2c90-4e94-8f9b-9a81d7145f78.jpg?interpolation=lanczos-none&size=x_large_cover&output-format=jpg&output-quality=70","x_medium":"https://a2.muscache.com/im/pictures/cb6a8cce-2c90-4e94-8f9b-9a81d7145f78.jpg?aki_policy=x_medium","x_small":"https://a2.muscache.com/im/pictures/cb6a8cce-2c90-4e94-8f9b-9a81d7145f78.jpg?aki_policy=x_small","xl_picture":"https://a2.muscache.com/im/pictures/cb6a8cce-2c90-4e94-8f9b-9a81d7145f78.jpg?aki_policy=x_large","xx_large":"https://a2.muscache.com/im/pictures/cb6a8cce-2c90-4e94-8f9b-9a81d7145f78.jpg?aki_policy=xx_large"},{"id":154310933,"picture":"https://a2.muscache.com/im/pictures/4e1c9e76-c83f-440a-b14c-775b9859b869.jpg?aki_policy=large","sort_order":7,"caption":"","large":"https://a2.muscache.com/im/pictures/4e1c9e76-c83f-440a-b14c-775b9859b869.jpg?aki_policy=large","large_cover":"https://a2.muscache.com/ac/pictures/4e1c9e76-c83f-440a-b14c-775b9859b869.jpg?interpolation=lanczos-none&size=large_cover&output-format=jpg&output-quality=70","medium":"https://a2.muscache.com/im/pictures/4e1c9e76-c83f-440a-b14c-775b9859b869.jpg?aki_policy=medium","mini_square":"https://a2.muscache.com/im/pictures/4e1c9e76-c83f-440a-b14c-775b9859b869.jpg?aki_policy=mini_square","small":"https://a2.muscache.com/im/pictures/4e1c9e76-c83f-440a-b14c-775b9859b869.jpg?aki_policy=small","thumbnail":"https://a2.muscache.com/im/pictures/4e1c9e76-c83f-440a-b14c-775b9859b869.jpg?aki_policy=small","x_large":"https://a2.muscache.com/im/pictures/4e1c9e76-c83f-440a-b14c-775b9859b869.jpg?aki_policy=x_large","x_large_cover":"https://a2.muscache.com/ac/pictures/4e1c9e76-c83f-440a-b14c-775b9859b869.jpg?interpolation=lanczos-none&size=x_large_cover&output-format=jpg&output-quality=70","x_medium":"https://a2.muscache.com/im/pictures/4e1c9e76-c83f-440a-b14c-775b9859b869.jpg?aki_policy=x_medium","x_small":"https://a2.muscache.com/im/pictures/4e1c9e76-c83f-440a-b14c-775b9859b869.jpg?aki_policy=x_small","xl_picture":"https://a2.muscache.com/im/pictures/4e1c9e76-c83f-440a-b14c-775b9859b869.jpg?aki_policy=x_large","xx_large":"https://a2.muscache.com/im/pictures/4e1c9e76-c83f-440a-b14c-775b9859b869.jpg?aki_policy=xx_large"},{"id":154310972,"picture":"https://a2.muscache.com/im/pictures/f15ee90c-5185-4d77-85ed-3d6dfadd1427.jpg?aki_policy=large","sort_order":8,"caption":"","large":"https://a2.muscache.com/im/pictures/f15ee90c-5185-4d77-85ed-3d6dfadd1427.jpg?aki_policy=large","large_cover":"https://a2.muscache.com/ac/pictures/f15ee90c-5185-4d77-85ed-3d6dfadd1427.jpg?interpolation=lanczos-none&size=large_cover&output-format=jpg&output-quality=70","medium":"https://a2.muscache.com/im/pictures/f15ee90c-5185-4d77-85ed-3d6dfadd1427.jpg?aki_policy=medium","mini_square":"https://a2.muscache.com/im/pictures/f15ee90c-5185-4d77-85ed-3d6dfadd1427.jpg?aki_policy=mini_square","small":"https://a2.muscache.com/im/pictures/f15ee90c-5185-4d77-85ed-3d6dfadd1427.jpg?aki_policy=small","thumbnail":"https://a2.muscache.com/im/pictures/f15ee90c-5185-4d77-85ed-3d6dfadd1427.jpg?aki_policy=small","x_large":"https://a2.muscache.com/im/pictures/f15ee90c-5185-4d77-85ed-3d6dfadd1427.jpg?aki_policy=x_large","x_large_cover":"https://a2.muscache.com/ac/pictures/f15ee90c-5185-4d77-85ed-3d6dfadd1427.jpg?interpolation=lanczos-none&size=x_large_cover&output-format=jpg&output-quality=70","x_medium":"https://a2.muscache.com/im/pictures/f15ee90c-5185-4d77-85ed-3d6dfadd1427.jpg?aki_policy=x_medium","x_small":"https://a2.muscache.com/im/pictures/f15ee90c-5185-4d77-85ed-3d6dfadd1427.jpg?aki_policy=x_small","xl_picture":"https://a2.muscache.com/im/pictures/f15ee90c-5185-4d77-85ed-3d6dfadd1427.jpg?aki_policy=x_large","xx_large":"https://a2.muscache.com/im/pictures/f15ee90c-5185-4d77-85ed-3d6dfadd1427.jpg?aki_policy=xx_large"},{"id":154311021,"picture":"https://a2.muscache.com/im/pictures/88769bc9-da72-4ae9-8dc7-e2933288025c.jpg?aki_policy=large","sort_order":9,"caption":"","large":"https://a2.muscache.com/im/pictures/88769bc9-da72-4ae9-8dc7-e2933288025c.jpg?aki_policy=large","large_cover":"https://a2.muscache.com/ac/pictures/88769bc9-da72-4ae9-8dc7-e2933288025c.jpg?interpolation=lanczos-none&size=large_cover&output-format=jpg&output-quality=70","medium":"https://a2.muscache.com/im/pictures/88769bc9-da72-4ae9-8dc7-e2933288025c.jpg?aki_policy=medium","mini_square":"https://a2.muscache.com/im/pictures/88769bc9-da72-4ae9-8dc7-e2933288025c.jpg?aki_policy=mini_square","small":"https://a2.muscache.com/im/pictures/88769bc9-da72-4ae9-8dc7-e2933288025c.jpg?aki_policy=small","thumbnail":"https://a2.muscache.com/im/pictures/88769bc9-da72-4ae9-8dc7-e2933288025c.jpg?aki_policy=small","x_large":"https://a2.muscache.com/im/pictures/88769bc9-da72-4ae9-8dc7-e2933288025c.jpg?aki_policy=x_large","x_large_cover":"https://a2.muscache.com/ac/pictures/88769bc9-da72-4ae9-8dc7-e2933288025c.jpg?interpolation=lanczos-none&size=x_large_cover&output-format=jpg&output-quality=70","x_medium":"https://a2.muscache.com/im/pictures/88769bc9-da72-4ae9-8dc7-e2933288025c.jpg?aki_policy=x_medium","x_small":"https://a2.muscache.com/im/pictures/88769bc9-da72-4ae9-8dc7-e2933288025c.jpg?aki_policy=x_small","xl_picture":"https://a2.muscache.com/im/pictures/88769bc9-da72-4ae9-8dc7-e2933288025c.jpg?aki_policy=x_large","xx_large":"https://a2.muscache.com/im/pictures/88769bc9-da72-4ae9-8dc7-e2933288025c.jpg?aki_policy=xx_large"},{"id":154311088,"picture":"https://a2.muscache.com/im/pictures/015dbac6-5436-46a4-9d84-530b277433dc.jpg?aki_policy=large","sort_order":10,"caption":"","large":"https://a2.muscache.com/im/pictures/015dbac6-5436-46a4-9d84-530b277433dc.jpg?aki_policy=large","large_cover":"https://a2.muscache.com/ac/pictures/015dbac6-5436-46a4-9d84-530b277433dc.jpg?interpolation=lanczos-none&size=large_cover&output-format=jpg&output-quality=70","medium":"https://a2.muscache.com/im/pictures/015dbac6-5436-46a4-9d84-530b277433dc.jpg?aki_policy=medium","mini_square":"https://a2.muscache.com/im/pictures/015dbac6-5436-46a4-9d84-530b277433dc.jpg?aki_policy=mini_square","small":"https://a2.muscache.com/im/pictures/015dbac6-5436-46a4-9d84-530b277433dc.jpg?aki_policy=small","thumbnail":"https://a2.muscache.com/im/pictures/015dbac6-5436-46a4-9d84-530b277433dc.jpg?aki_policy=small","x_large":"https://a2.muscache.com/im/pictures/015dbac6-5436-46a4-9d84-530b277433dc.jpg?aki_policy=x_large","x_large_cover":"https://a2.muscache.com/ac/pictures/015dbac6-5436-46a4-9d84-530b277433dc.jpg?interpolation=lanczos-none&size=x_large_cover&output-format=jpg&output-quality=70","x_medium":"https://a2.muscache.com/im/pictures/015dbac6-5436-46a4-9d84-530b277433dc.jpg?aki_policy=x_medium","x_small":"https://a2.muscache.com/im/pictures/015dbac6-5436-46a4-9d84-530b277433dc.jpg?aki_policy=x_small","xl_picture":"https://a2.muscache.com/im/pictures/015dbac6-5436-46a4-9d84-530b277433dc.jpg?aki_policy=x_large","xx_large":"https://a2.muscache.com/im/pictures/015dbac6-5436-46a4-9d84-530b277433dc.jpg?aki_policy=xx_large"},{"id":154311138,"picture":"https://a2.muscache.com/im/pictures/7efd8ee8-ab1c-4ead-8a08-57b615bff4d5.jpg?aki_policy=large","sort_order":11,"caption":"","large":"https://a2.muscache.com/im/pictures/7efd8ee8-ab1c-4ead-8a08-57b615bff4d5.jpg?aki_policy=large","large_cover":"https://a2.muscache.com/ac/pictures/7efd8ee8-ab1c-4ead-8a08-57b615bff4d5.jpg?interpolation=lanczos-none&size=large_cover&output-format=jpg&output-quality=70","medium":"https://a2.muscache.com/im/pictures/7efd8ee8-ab1c-4ead-8a08-57b615bff4d5.jpg?aki_policy=medium","mini_square":"https://a2.muscache.com/im/pictures/7efd8ee8-ab1c-4ead-8a08-57b615bff4d5.jpg?aki_policy=mini_square","small":"https://a2.muscache.com/im/pictures/7efd8ee8-ab1c-4ead-8a08-57b615bff4d5.jpg?aki_policy=small","thumbnail":"https://a2.muscache.com/im/pictures/7efd8ee8-ab1c-4ead-8a08-57b615bff4d5.jpg?aki_policy=small","x_large":"https://a2.muscache.com/im/pictures/7efd8ee8-ab1c-4ead-8a08-57b615bff4d5.jpg?aki_policy=x_large","x_large_cover":"https://a2.muscache.com/ac/pictures/7efd8ee8-ab1c-4ead-8a08-57b615bff4d5.jpg?interpolation=lanczos-none&size=x_large_cover&output-format=jpg&output-quality=70","x_medium":"https://a2.muscache.com/im/pictures/7efd8ee8-ab1c-4ead-8a08-57b615bff4d5.jpg?aki_policy=x_medium","x_small":"https://a2.muscache.com/im/pictures/7efd8ee8-ab1c-4ead-8a08-57b615bff4d5.jpg?aki_policy=x_small","xl_picture":"https://a2.muscache.com/im/pictures/7efd8ee8-ab1c-4ead-8a08-57b615bff4d5.jpg?aki_policy=x_large","xx_large":"https://a2.muscache.com/im/pictures/7efd8ee8-ab1c-4ead-8a08-57b615bff4d5.jpg?aki_policy=xx_large"},{"id":154311177,"picture":"https://a2.muscache.com/im/pictures/c804d528-fedf-421f-9e5c-5ccfb7c52246.jpg?aki_policy=large","sort_order":12,"caption":"","large":"https://a2.muscache.com/im/pictures/c804d528-fedf-421f-9e5c-5ccfb7c52246.jpg?aki_policy=large","large_cover":"https://a2.muscache.com/ac/pictures/c804d528-fedf-421f-9e5c-5ccfb7c52246.jpg?interpolation=lanczos-none&size=large_cover&output-format=jpg&output-quality=70","medium":"https://a2.muscache.com/im/pictures/c804d528-fedf-421f-9e5c-5ccfb7c52246.jpg?aki_policy=medium","mini_square":"https://a2.muscache.com/im/pictures/c804d528-fedf-421f-9e5c-5ccfb7c52246.jpg?aki_policy=mini_square","small":"https://a2.muscache.com/im/pictures/c804d528-fedf-421f-9e5c-5ccfb7c52246.jpg?aki_policy=small","thumbnail":"https://a2.muscache.com/im/pictures/c804d528-fedf-421f-9e5c-5ccfb7c52246.jpg?aki_policy=small","x_large":"https://a2.muscache.com/im/pictures/c804d528-fedf-421f-9e5c-5ccfb7c52246.jpg?aki_policy=x_large","x_large_cover":"https://a2.muscache.com/ac/pictures/c804d528-fedf-421f-9e5c-5ccfb7c52246.jpg?interpolation=lanczos-none&size=x_large_cover&output-format=jpg&output-quality=70","x_medium":"https://a2.muscache.com/im/pictures/c804d528-fedf-421f-9e5c-5ccfb7c52246.jpg?aki_policy=x_medium","x_small":"https://a2.muscache.com/im/pictures/c804d528-fedf-421f-9e5c-5ccfb7c52246.jpg?aki_policy=x_small","xl_picture":"https://a2.muscache.com/im/pictures/c804d528-fedf-421f-9e5c-5ccfb7c52246.jpg?aki_policy=x_large","xx_large":"https://a2.muscache.com/im/pictures/c804d528-fedf-421f-9e5c-5ccfb7c52246.jpg?aki_policy=xx_large"},{"id":154311209,"picture":"https://a2.muscache.com/im/pictures/5a28062f-ed24-44fa-ab41-e91203e7a3e2.jpg?aki_policy=large","sort_order":13,"caption":"","large":"https://a2.muscache.com/im/pictures/5a28062f-ed24-44fa-ab41-e91203e7a3e2.jpg?aki_policy=large","large_cover":"https://a2.muscache.com/ac/pictures/5a28062f-ed24-44fa-ab41-e91203e7a3e2.jpg?interpolation=lanczos-none&size=large_cover&output-format=jpg&output-quality=70","medium":"https://a2.muscache.com/im/pictures/5a28062f-ed24-44fa-ab41-e91203e7a3e2.jpg?aki_policy=medium","mini_square":"https://a2.muscache.com/im/pictures/5a28062f-ed24-44fa-ab41-e91203e7a3e2.jpg?aki_policy=mini_square","small":"https://a2.muscache.com/im/pictures/5a28062f-ed24-44fa-ab41-e91203e7a3e2.jpg?aki_policy=small","thumbnail":"https://a2.muscache.com/im/pictures/5a28062f-ed24-44fa-ab41-e91203e7a3e2.jpg?aki_policy=small","x_large":"https://a2.muscache.com/im/pictures/5a28062f-ed24-44fa-ab41-e91203e7a3e2.jpg?aki_policy=x_large","x_large_cover":"https://a2.muscache.com/ac/pictures/5a28062f-ed24-44fa-ab41-e91203e7a3e2.jpg?interpolation=lanczos-none&size=x_large_cover&output-format=jpg&output-quality=70","x_medium":"https://a2.muscache.com/im/pictures/5a28062f-ed24-44fa-ab41-e91203e7a3e2.jpg?aki_policy=x_medium","x_small":"https://a2.muscache.com/im/pictures/5a28062f-ed24-44fa-ab41-e91203e7a3e2.jpg?aki_policy=x_small","xl_picture":"https://a2.muscache.com/im/pictures/5a28062f-ed24-44fa-ab41-e91203e7a3e2.jpg?aki_policy=x_large","xx_large":"https://a2.muscache.com/im/pictures/5a28062f-ed24-44fa-ab41-e91203e7a3e2.jpg?aki_policy=xx_large"},{"id":154311247,"picture":"https://a2.muscache.com/im/pictures/d7a80174-f8cb-4ba1-aefc-c5f22ad6e9fa.jpg?aki_policy=large","sort_order":14,"caption":"","large":"https://a2.muscache.com/im/pictures/d7a80174-f8cb-4ba1-aefc-c5f22ad6e9fa.jpg?aki_policy=large","large_cover":"https://a2.muscache.com/ac/pictures/d7a80174-f8cb-4ba1-aefc-c5f22ad6e9fa.jpg?interpolation=lanczos-none&size=large_cover&output-format=jpg&output-quality=70","medium":"https://a2.muscache.com/im/pictures/d7a80174-f8cb-4ba1-aefc-c5f22ad6e9fa.jpg?aki_policy=medium","mini_square":"https://a2.muscache.com/im/pictures/d7a80174-f8cb-4ba1-aefc-c5f22ad6e9fa.jpg?aki_policy=mini_square","small":"https://a2.muscache.com/im/pictures/d7a80174-f8cb-4ba1-aefc-c5f22ad6e9fa.jpg?aki_policy=small","thumbnail":"https://a2.muscache.com/im/pictures/d7a80174-f8cb-4ba1-aefc-c5f22ad6e9fa.jpg?aki_policy=small","x_large":"https://a2.muscache.com/im/pictures/d7a80174-f8cb-4ba1-aefc-c5f22ad6e9fa.jpg?aki_policy=x_large","x_large_cover":"https://a2.muscache.com/ac/pictures/d7a80174-f8cb-4ba1-aefc-c5f22ad6e9fa.jpg?interpolation=lanczos-none&size=x_large_cover&output-format=jpg&output-quality=70","x_medium":"https://a2.muscache.com/im/pictures/d7a80174-f8cb-4ba1-aefc-c5f22ad6e9fa.jpg?aki_policy=x_medium","x_small":"https://a2.muscache.com/im/pictures/d7a80174-f8cb-4ba1-aefc-c5f22ad6e9fa.jpg?aki_policy=x_small","xl_picture":"https://a2.muscache.com/im/pictures/d7a80174-f8cb-4ba1-aefc-c5f22ad6e9fa.jpg?aki_policy=x_large","xx_large":"https://a2.muscache.com/im/pictures/d7a80174-f8cb-4ba1-aefc-c5f22ad6e9fa.jpg?aki_policy=xx_large"},{"id":154311279,"picture":"https://a2.muscache.com/im/pictures/dd785b8b-36a1-44ea-bec4-f352db62f3a4.jpg?aki_policy=large","sort_order":15,"caption":"","large":"https://a2.muscache.com/im/pictures/dd785b8b-36a1-44ea-bec4-f352db62f3a4.jpg?aki_policy=large","large_cover":"https://a2.muscache.com/ac/pictures/dd785b8b-36a1-44ea-bec4-f352db62f3a4.jpg?interpolation=lanczos-none&size=large_cover&output-format=jpg&output-quality=70","medium":"https://a2.muscache.com/im/pictures/dd785b8b-36a1-44ea-bec4-f352db62f3a4.jpg?aki_policy=medium","mini_square":"https://a2.muscache.com/im/pictures/dd785b8b-36a1-44ea-bec4-f352db62f3a4.jpg?aki_policy=mini_square","small":"https://a2.muscache.com/im/pictures/dd785b8b-36a1-44ea-bec4-f352db62f3a4.jpg?aki_policy=small","thumbnail":"https://a2.muscache.com/im/pictures/dd785b8b-36a1-44ea-bec4-f352db62f3a4.jpg?aki_policy=small","x_large":"https://a2.muscache.com/im/pictures/dd785b8b-36a1-44ea-bec4-f352db62f3a4.jpg?aki_policy=x_large","x_large_cover":"https://a2.muscache.com/ac/pictures/dd785b8b-36a1-44ea-bec4-f352db62f3a4.jpg?interpolation=lanczos-none&size=x_large_cover&output-format=jpg&output-quality=70","x_medium":"https://a2.muscache.com/im/pictures/dd785b8b-36a1-44ea-bec4-f352db62f3a4.jpg?aki_policy=x_medium","x_small":"https://a2.muscache.com/im/pictures/dd785b8b-36a1-44ea-bec4-f352db62f3a4.jpg?aki_policy=x_small","xl_picture":"https://a2.muscache.com/im/pictures/dd785b8b-36a1-44ea-bec4-f352db62f3a4.jpg?aki_policy=x_large","xx_large":"https://a2.muscache.com/im/pictures/dd785b8b-36a1-44ea-bec4-f352db62f3a4.jpg?aki_policy=xx_large"},{"id":154311323,"picture":"https://a2.muscache.com/im/pictures/f0403dc8-9adb-4b90-9ed1-d112f4d622a8.jpg?aki_policy=large","sort_order":16,"caption":"","large":"https://a2.muscache.com/im/pictures/f0403dc8-9adb-4b90-9ed1-d112f4d622a8.jpg?aki_policy=large","large_cover":"https://a2.muscache.com/ac/pictures/f0403dc8-9adb-4b90-9ed1-d112f4d622a8.jpg?interpolation=lanczos-none&size=large_cover&output-format=jpg&output-quality=70","medium":"https://a2.muscache.com/im/pictures/f0403dc8-9adb-4b90-9ed1-d112f4d622a8.jpg?aki_policy=medium","mini_square":"https://a2.muscache.com/im/pictures/f0403dc8-9adb-4b90-9ed1-d112f4d622a8.jpg?aki_policy=mini_square","small":"https://a2.muscache.com/im/pictures/f0403dc8-9adb-4b90-9ed1-d112f4d622a8.jpg?aki_policy=small","thumbnail":"https://a2.muscache.com/im/pictures/f0403dc8-9adb-4b90-9ed1-d112f4d622a8.jpg?aki_policy=small","x_large":"https://a2.muscache.com/im/pictures/f0403dc8-9adb-4b90-9ed1-d112f4d622a8.jpg?aki_policy=x_large","x_large_cover":"https://a2.muscache.com/ac/pictures/f0403dc8-9adb-4b90-9ed1-d112f4d622a8.jpg?interpolation=lanczos-none&size=x_large_cover&output-format=jpg&output-quality=70","x_medium":"https://a2.muscache.com/im/pictures/f0403dc8-9adb-4b90-9ed1-d112f4d622a8.jpg?aki_policy=x_medium","x_small":"https://a2.muscache.com/im/pictures/f0403dc8-9adb-4b90-9ed1-d112f4d622a8.jpg?aki_policy=x_small","xl_picture":"https://a2.muscache.com/im/pictures/f0403dc8-9adb-4b90-9ed1-d112f4d622a8.jpg?aki_policy=x_large","xx_large":"https://a2.muscache.com/im/pictures/f0403dc8-9adb-4b90-9ed1-d112f4d622a8.jpg?aki_policy=xx_large"},{"id":154311359,"picture":"https://a2.muscache.com/im/pictures/5e5b85a1-077c-4b6e-adec-6803eac219dc.jpg?aki_policy=large","sort_order":17,"caption":"","large":"https://a2.muscache.com/im/pictures/5e5b85a1-077c-4b6e-adec-6803eac219dc.jpg?aki_policy=large","large_cover":"https://a2.muscache.com/ac/pictures/5e5b85a1-077c-4b6e-adec-6803eac219dc.jpg?interpolation=lanczos-none&size=large_cover&output-format=jpg&output-quality=70","medium":"https://a2.muscache.com/im/pictures/5e5b85a1-077c-4b6e-adec-6803eac219dc.jpg?aki_policy=medium","mini_square":"https://a2.muscache.com/im/pictures/5e5b85a1-077c-4b6e-adec-6803eac219dc.jpg?aki_policy=mini_square","small":"https://a2.muscache.com/im/pictures/5e5b85a1-077c-4b6e-adec-6803eac219dc.jpg?aki_policy=small","thumbnail":"https://a2.muscache.com/im/pictures/5e5b85a1-077c-4b6e-adec-6803eac219dc.jpg?aki_policy=small","x_large":"https://a2.muscache.com/im/pictures/5e5b85a1-077c-4b6e-adec-6803eac219dc.jpg?aki_policy=x_large","x_large_cover":"https://a2.muscache.com/ac/pictures/5e5b85a1-077c-4b6e-adec-6803eac219dc.jpg?interpolation=lanczos-none&size=x_large_cover&output-format=jpg&output-quality=70","x_medium":"https://a2.muscache.com/im/pictures/5e5b85a1-077c-4b6e-adec-6803eac219dc.jpg?aki_policy=x_medium","x_small":"https://a2.muscache.com/im/pictures/5e5b85a1-077c-4b6e-adec-6803eac219dc.jpg?aki_policy=x_small","xl_picture":"https://a2.muscache.com/im/pictures/5e5b85a1-077c-4b6e-adec-6803eac219dc.jpg?aki_policy=x_large","xx_large":"https://a2.muscache.com/im/pictures/5e5b85a1-077c-4b6e-adec-6803eac219dc.jpg?aki_policy=xx_large"},{"id":154311412,"picture":"https://a2.muscache.com/im/pictures/66ce33e1-b477-4ed7-aca7-f3228028bd7e.jpg?aki_policy=large","sort_order":18,"caption":"","large":"https://a2.muscache.com/im/pictures/66ce33e1-b477-4ed7-aca7-f3228028bd7e.jpg?aki_policy=large","large_cover":"https://a2.muscache.com/ac/pictures/66ce33e1-b477-4ed7-aca7-f3228028bd7e.jpg?interpolation=lanczos-none&size=large_cover&output-format=jpg&output-quality=70","medium":"https://a2.muscache.com/im/pictures/66ce33e1-b477-4ed7-aca7-f3228028bd7e.jpg?aki_policy=medium","mini_square":"https://a2.muscache.com/im/pictures/66ce33e1-b477-4ed7-aca7-f3228028bd7e.jpg?aki_policy=mini_square","small":"https://a2.muscache.com/im/pictures/66ce33e1-b477-4ed7-aca7-f3228028bd7e.jpg?aki_policy=small","thumbnail":"https://a2.muscache.com/im/pictures/66ce33e1-b477-4ed7-aca7-f3228028bd7e.jpg?aki_policy=small","x_large":"https://a2.muscache.com/im/pictures/66ce33e1-b477-4ed7-aca7-f3228028bd7e.jpg?aki_policy=x_large","x_large_cover":"https://a2.muscache.com/ac/pictures/66ce33e1-b477-4ed7-aca7-f3228028bd7e.jpg?interpolation=lanczos-none&size=x_large_cover&output-format=jpg&output-quality=70","x_medium":"https://a2.muscache.com/im/pictures/66ce33e1-b477-4ed7-aca7-f3228028bd7e.jpg?aki_policy=x_medium","x_small":"https://a2.muscache.com/im/pictures/66ce33e1-b477-4ed7-aca7-f3228028bd7e.jpg?aki_policy=x_small","xl_picture":"https://a2.muscache.com/im/pictures/66ce33e1-b477-4ed7-aca7-f3228028bd7e.jpg?aki_policy=x_large","xx_large":"https://a2.muscache.com/im/pictures/66ce33e1-b477-4ed7-aca7-f3228028bd7e.jpg?aki_policy=xx_large"},{"id":154311491,"picture":"https://a2.muscache.com/im/pictures/b2245e3b-9c0e-4934-8519-f7e5b9568e3f.jpg?aki_policy=large","sort_order":19,"caption":"","large":"https://a2.muscache.com/im/pictures/b2245e3b-9c0e-4934-8519-f7e5b9568e3f.jpg?aki_policy=large","large_cover":"https://a2.muscache.com/ac/pictures/b2245e3b-9c0e-4934-8519-f7e5b9568e3f.jpg?interpolation=lanczos-none&size=large_cover&output-format=jpg&output-quality=70","medium":"https://a2.muscache.com/im/pictures/b2245e3b-9c0e-4934-8519-f7e5b9568e3f.jpg?aki_policy=medium","mini_square":"https://a2.muscache.com/im/pictures/b2245e3b-9c0e-4934-8519-f7e5b9568e3f.jpg?aki_policy=mini_square","small":"https://a2.muscache.com/im/pictures/b2245e3b-9c0e-4934-8519-f7e5b9568e3f.jpg?aki_policy=small","thumbnail":"https://a2.muscache.com/im/pictures/b2245e3b-9c0e-4934-8519-f7e5b9568e3f.jpg?aki_policy=small","x_large":"https://a2.muscache.com/im/pictures/b2245e3b-9c0e-4934-8519-f7e5b9568e3f.jpg?aki_policy=x_large","x_large_cover":"https://a2.muscache.com/ac/pictures/b2245e3b-9c0e-4934-8519-f7e5b9568e3f.jpg?interpolation=lanczos-none&size=x_large_cover&output-format=jpg&output-quality=70","x_medium":"https://a2.muscache.com/im/pictures/b2245e3b-9c0e-4934-8519-f7e5b9568e3f.jpg?aki_policy=x_medium","x_small":"https://a2.muscache.com/im/pictures/b2245e3b-9c0e-4934-8519-f7e5b9568e3f.jpg?aki_policy=x_small","xl_picture":"https://a2.muscache.com/im/pictures/b2245e3b-9c0e-4934-8519-f7e5b9568e3f.jpg?aki_policy=x_large","xx_large":"https://a2.muscache.com/im/pictures/b2245e3b-9c0e-4934-8519-f7e5b9568e3f.jpg?aki_policy=xx_large"},{"id":154311440,"picture":"https://a2.muscache.com/im/pictures/962b11f1-375d-4eb5-ab2d-72aa2635a504.jpg?aki_policy=large","sort_order":20,"caption":"","large":"https://a2.muscache.com/im/pictures/962b11f1-375d-4eb5-ab2d-72aa2635a504.jpg?aki_policy=large","large_cover":"https://a2.muscache.com/ac/pictures/962b11f1-375d-4eb5-ab2d-72aa2635a504.jpg?interpolation=lanczos-none&size=large_cover&output-format=jpg&output-quality=70","medium":"https://a2.muscache.com/im/pictures/962b11f1-375d-4eb5-ab2d-72aa2635a504.jpg?aki_policy=medium","mini_square":"https://a2.muscache.com/im/pictures/962b11f1-375d-4eb5-ab2d-72aa2635a504.jpg?aki_policy=mini_square","small":"https://a2.muscache.com/im/pictures/962b11f1-375d-4eb5-ab2d-72aa2635a504.jpg?aki_policy=small","thumbnail":"https://a2.muscache.com/im/pictures/962b11f1-375d-4eb5-ab2d-72aa2635a504.jpg?aki_policy=small","x_large":"https://a2.muscache.com/im/pictures/962b11f1-375d-4eb5-ab2d-72aa2635a504.jpg?aki_policy=x_large","x_large_cover":"https://a2.muscache.com/ac/pictures/962b11f1-375d-4eb5-ab2d-72aa2635a504.jpg?interpolation=lanczos-none&size=x_large_cover&output-format=jpg&output-quality=70","x_medium":"https://a2.muscache.com/im/pictures/962b11f1-375d-4eb5-ab2d-72aa2635a504.jpg?aki_policy=x_medium","x_small":"https://a2.muscache.com/im/pictures/962b11f1-375d-4eb5-ab2d-72aa2635a504.jpg?aki_policy=x_small","xl_picture":"https://a2.muscache.com/im/pictures/962b11f1-375d-4eb5-ab2d-72aa2635a504.jpg?aki_policy=x_large","xx_large":"https://a2.muscache.com/im/pictures/962b11f1-375d-4eb5-ab2d-72aa2635a504.jpg?aki_policy=xx_large"},{"id":154311524,"picture":"https://a2.muscache.com/im/pictures/cbeace76-14cf-4614-a94d-4b7da894d95b.jpg?aki_policy=large","sort_order":21,"caption":"","large":"https://a2.muscache.com/im/pictures/cbeace76-14cf-4614-a94d-4b7da894d95b.jpg?aki_policy=large","large_cover":"https://a2.muscache.com/ac/pictures/cbeace76-14cf-4614-a94d-4b7da894d95b.jpg?interpolation=lanczos-none&size=large_cover&output-format=jpg&output-quality=70","medium":"https://a2.muscache.com/im/pictures/cbeace76-14cf-4614-a94d-4b7da894d95b.jpg?aki_policy=medium","mini_square":"https://a2.muscache.com/im/pictures/cbeace76-14cf-4614-a94d-4b7da894d95b.jpg?aki_policy=mini_square","small":"https://a2.muscache.com/im/pictures/cbeace76-14cf-4614-a94d-4b7da894d95b.jpg?aki_policy=small","thumbnail":"https://a2.muscache.com/im/pictures/cbeace76-14cf-4614-a94d-4b7da894d95b.jpg?aki_policy=small","x_large":"https://a2.muscache.com/im/pictures/cbeace76-14cf-4614-a94d-4b7da894d95b.jpg?aki_policy=x_large","x_large_cover":"https://a2.muscache.com/ac/pictures/cbeace76-14cf-4614-a94d-4b7da894d95b.jpg?interpolation=lanczos-none&size=x_large_cover&output-format=jpg&output-quality=70","x_medium":"https://a2.muscache.com/im/pictures/cbeace76-14cf-4614-a94d-4b7da894d95b.jpg?aki_policy=x_medium","x_small":"https://a2.muscache.com/im/pictures/cbeace76-14cf-4614-a94d-4b7da894d95b.jpg?aki_policy=x_small","xl_picture":"https://a2.muscache.com/im/pictures/cbeace76-14cf-4614-a94d-4b7da894d95b.jpg?aki_policy=x_large","xx_large":"https://a2.muscache.com/im/pictures/cbeace76-14cf-4614-a94d-4b7da894d95b.jpg?aki_policy=xx_large"},{"id":154311557,"picture":"https://a2.muscache.com/im/pictures/9b798a60-e0e9-4544-98d5-f3312c3e676e.jpg?aki_policy=large","sort_order":22,"caption":"","large":"https://a2.muscache.com/im/pictures/9b798a60-e0e9-4544-98d5-f3312c3e676e.jpg?aki_policy=large","large_cover":"https://a2.muscache.com/ac/pictures/9b798a60-e0e9-4544-98d5-f3312c3e676e.jpg?interpolation=lanczos-none&size=large_cover&output-format=jpg&output-quality=70","medium":"https://a2.muscache.com/im/pictures/9b798a60-e0e9-4544-98d5-f3312c3e676e.jpg?aki_policy=medium","mini_square":"https://a2.muscache.com/im/pictures/9b798a60-e0e9-4544-98d5-f3312c3e676e.jpg?aki_policy=mini_square","small":"https://a2.muscache.com/im/pictures/9b798a60-e0e9-4544-98d5-f3312c3e676e.jpg?aki_policy=small","thumbnail":"https://a2.muscache.com/im/pictures/9b798a60-e0e9-4544-98d5-f3312c3e676e.jpg?aki_policy=small","x_large":"https://a2.muscache.com/im/pictures/9b798a60-e0e9-4544-98d5-f3312c3e676e.jpg?aki_policy=x_large","x_large_cover":"https://a2.muscache.com/ac/pictures/9b798a60-e0e9-4544-98d5-f3312c3e676e.jpg?interpolation=lanczos-none&size=x_large_cover&output-format=jpg&output-quality=70","x_medium":"https://a2.muscache.com/im/pictures/9b798a60-e0e9-4544-98d5-f3312c3e676e.jpg?aki_policy=x_medium","x_small":"https://a2.muscache.com/im/pictures/9b798a60-e0e9-4544-98d5-f3312c3e676e.jpg?aki_policy=x_small","xl_picture":"https://a2.muscache.com/im/pictures/9b798a60-e0e9-4544-98d5-f3312c3e676e.jpg?aki_policy=x_large","xx_large":"https://a2.muscache.com/im/pictures/9b798a60-e0e9-4544-98d5-f3312c3e676e.jpg?aki_policy=xx_large"},{"id":154311606,"picture":"https://a2.muscache.com/im/pictures/4587993e-bfc5-4148-8778-40e399ea965e.jpg?aki_policy=large","sort_order":23,"caption":"","large":"https://a2.muscache.com/im/pictures/4587993e-bfc5-4148-8778-40e399ea965e.jpg?aki_policy=large","large_cover":"https://a2.muscache.com/ac/pictures/4587993e-bfc5-4148-8778-40e399ea965e.jpg?interpolation=lanczos-none&size=large_cover&output-format=jpg&output-quality=70","medium":"https://a2.muscache.com/im/pictures/4587993e-bfc5-4148-8778-40e399ea965e.jpg?aki_policy=medium","mini_square":"https://a2.muscache.com/im/pictures/4587993e-bfc5-4148-8778-40e399ea965e.jpg?aki_policy=mini_square","small":"https://a2.muscache.com/im/pictures/4587993e-bfc5-4148-8778-40e399ea965e.jpg?aki_policy=small","thumbnail":"https://a2.muscache.com/im/pictures/4587993e-bfc5-4148-8778-40e399ea965e.jpg?aki_policy=small","x_large":"https://a2.muscache.com/im/pictures/4587993e-bfc5-4148-8778-40e399ea965e.jpg?aki_policy=x_large","x_large_cover":"https://a2.muscache.com/ac/pictures/4587993e-bfc5-4148-8778-40e399ea965e.jpg?interpolation=lanczos-none&size=x_large_cover&output-format=jpg&output-quality=70","x_medium":"https://a2.muscache.com/im/pictures/4587993e-bfc5-4148-8778-40e399ea965e.jpg?aki_policy=x_medium","x_small":"https://a2.muscache.com/im/pictures/4587993e-bfc5-4148-8778-40e399ea965e.jpg?aki_policy=x_small","xl_picture":"https://a2.muscache.com/im/pictures/4587993e-bfc5-4148-8778-40e399ea965e.jpg?aki_policy=x_large","xx_large":"https://a2.muscache.com/im/pictures/4587993e-bfc5-4148-8778-40e399ea965e.jpg?aki_policy=xx_large"},{"id":154311637,"picture":"https://a2.muscache.com/im/pictures/44e1dc27-91b2-4357-80cc-01c451fc5bca.jpg?aki_policy=large","sort_order":24,"caption":"","large":"https://a2.muscache.com/im/pictures/44e1dc27-91b2-4357-80cc-01c451fc5bca.jpg?aki_policy=large","large_cover":"https://a2.muscache.com/ac/pictures/44e1dc27-91b2-4357-80cc-01c451fc5bca.jpg?interpolation=lanczos-none&size=large_cover&output-format=jpg&output-quality=70","medium":"https://a2.muscache.com/im/pictures/44e1dc27-91b2-4357-80cc-01c451fc5bca.jpg?aki_policy=medium","mini_square":"https://a2.muscache.com/im/pictures/44e1dc27-91b2-4357-80cc-01c451fc5bca.jpg?aki_policy=mini_square","small":"https://a2.muscache.com/im/pictures/44e1dc27-91b2-4357-80cc-01c451fc5bca.jpg?aki_policy=small","thumbnail":"https://a2.muscache.com/im/pictures/44e1dc27-91b2-4357-80cc-01c451fc5bca.jpg?aki_policy=small","x_large":"https://a2.muscache.com/im/pictures/44e1dc27-91b2-4357-80cc-01c451fc5bca.jpg?aki_policy=x_large","x_large_cover":"https://a2.muscache.com/ac/pictures/44e1dc27-91b2-4357-80cc-01c451fc5bca.jpg?interpolation=lanczos-none&size=x_large_cover&output-format=jpg&output-quality=70","x_medium":"https://a2.muscache.com/im/pictures/44e1dc27-91b2-4357-80cc-01c451fc5bca.jpg?aki_policy=x_medium","x_small":"https://a2.muscache.com/im/pictures/44e1dc27-91b2-4357-80cc-01c451fc5bca.jpg?aki_policy=x_small","xl_picture":"https://a2.muscache.com/im/pictures/44e1dc27-91b2-4357-80cc-01c451fc5bca.jpg?aki_policy=x_large","xx_large":"https://a2.muscache.com/im/pictures/44e1dc27-91b2-4357-80cc-01c451fc5bca.jpg?aki_policy=xx_large"},{"id":154311663,"picture":"https://a2.muscache.com/im/pictures/05bc28f9-3304-4bae-9b67-77d0931f67e4.jpg?aki_policy=large","sort_order":25,"caption":"","large":"https://a2.muscache.com/im/pictures/05bc28f9-3304-4bae-9b67-77d0931f67e4.jpg?aki_policy=large","large_cover":"https://a2.muscache.com/ac/pictures/05bc28f9-3304-4bae-9b67-77d0931f67e4.jpg?interpolation=lanczos-none&size=large_cover&output-format=jpg&output-quality=70","medium":"https://a2.muscache.com/im/pictures/05bc28f9-3304-4bae-9b67-77d0931f67e4.jpg?aki_policy=medium","mini_square":"https://a2.muscache.com/im/pictures/05bc28f9-3304-4bae-9b67-77d0931f67e4.jpg?aki_policy=mini_square","small":"https://a2.muscache.com/im/pictures/05bc28f9-3304-4bae-9b67-77d0931f67e4.jpg?aki_policy=small","thumbnail":"https://a2.muscache.com/im/pictures/05bc28f9-3304-4bae-9b67-77d0931f67e4.jpg?aki_policy=small","x_large":"https://a2.muscache.com/im/pictures/05bc28f9-3304-4bae-9b67-77d0931f67e4.jpg?aki_policy=x_large","x_large_cover":"https://a2.muscache.com/ac/pictures/05bc28f9-3304-4bae-9b67-77d0931f67e4.jpg?interpolation=lanczos-none&size=x_large_cover&output-format=jpg&output-quality=70","x_medium":"https://a2.muscache.com/im/pictures/05bc28f9-3304-4bae-9b67-77d0931f67e4.jpg?aki_policy=x_medium","x_small":"https://a2.muscache.com/im/pictures/05bc28f9-3304-4bae-9b67-77d0931f67e4.jpg?aki_policy=x_small","xl_picture":"https://a2.muscache.com/im/pictures/05bc28f9-3304-4bae-9b67-77d0931f67e4.jpg?aki_policy=x_large","xx_large":"https://a2.muscache.com/im/pictures/05bc28f9-3304-4bae-9b67-77d0931f67e4.jpg?aki_policy=xx_large"},{"id":154311696,"picture":"https://a2.muscache.com/im/pictures/7ec2eed8-aca9-4815-b702-1f6c0dd9f13d.jpg?aki_policy=large","sort_order":26,"caption":"","large":"https://a2.muscache.com/im/pictures/7ec2eed8-aca9-4815-b702-1f6c0dd9f13d.jpg?aki_policy=large","large_cover":"https://a2.muscache.com/ac/pictures/7ec2eed8-aca9-4815-b702-1f6c0dd9f13d.jpg?interpolation=lanczos-none&size=large_cover&output-format=jpg&output-quality=70","medium":"https://a2.muscache.com/im/pictures/7ec2eed8-aca9-4815-b702-1f6c0dd9f13d.jpg?aki_policy=medium","mini_square":"https://a2.muscache.com/im/pictures/7ec2eed8-aca9-4815-b702-1f6c0dd9f13d.jpg?aki_policy=mini_square","small":"https://a2.muscache.com/im/pictures/7ec2eed8-aca9-4815-b702-1f6c0dd9f13d.jpg?aki_policy=small","thumbnail":"https://a2.muscache.com/im/pictures/7ec2eed8-aca9-4815-b702-1f6c0dd9f13d.jpg?aki_policy=small","x_large":"https://a2.muscache.com/im/pictures/7ec2eed8-aca9-4815-b702-1f6c0dd9f13d.jpg?aki_policy=x_large","x_large_cover":"https://a2.muscache.com/ac/pictures/7ec2eed8-aca9-4815-b702-1f6c0dd9f13d.jpg?interpolation=lanczos-none&size=x_large_cover&output-format=jpg&output-quality=70","x_medium":"https://a2.muscache.com/im/pictures/7ec2eed8-aca9-4815-b702-1f6c0dd9f13d.jpg?aki_policy=x_medium","x_small":"https://a2.muscache.com/im/pictures/7ec2eed8-aca9-4815-b702-1f6c0dd9f13d.jpg?aki_policy=x_small","xl_picture":"https://a2.muscache.com/im/pictures/7ec2eed8-aca9-4815-b702-1f6c0dd9f13d.jpg?aki_policy=x_large","xx_large":"https://a2.muscache.com/im/pictures/7ec2eed8-aca9-4815-b702-1f6c0dd9f13d.jpg?aki_policy=xx_large"},{"id":154311740,"picture":"https://a2.muscache.com/im/pictures/04937866-5885-4bf9-a025-2ba0be69bb48.jpg?aki_policy=large","sort_order":27,"caption":"","large":"https://a2.muscache.com/im/pictures/04937866-5885-4bf9-a025-2ba0be69bb48.jpg?aki_policy=large","large_cover":"https://a2.muscache.com/ac/pictures/04937866-5885-4bf9-a025-2ba0be69bb48.jpg?interpolation=lanczos-none&size=large_cover&output-format=jpg&output-quality=70","medium":"https://a2.muscache.com/im/pictures/04937866-5885-4bf9-a025-2ba0be69bb48.jpg?aki_policy=medium","mini_square":"https://a2.muscache.com/im/pictures/04937866-5885-4bf9-a025-2ba0be69bb48.jpg?aki_policy=mini_square","small":"https://a2.muscache.com/im/pictures/04937866-5885-4bf9-a025-2ba0be69bb48.jpg?aki_policy=small","thumbnail":"https://a2.muscache.com/im/pictures/04937866-5885-4bf9-a025-2ba0be69bb48.jpg?aki_policy=small","x_large":"https://a2.muscache.com/im/pictures/04937866-5885-4bf9-a025-2ba0be69bb48.jpg?aki_policy=x_large","x_large_cover":"https://a2.muscache.com/ac/pictures/04937866-5885-4bf9-a025-2ba0be69bb48.jpg?interpolation=lanczos-none&size=x_large_cover&output-format=jpg&output-quality=70","x_medium":"https://a2.muscache.com/im/pictures/04937866-5885-4bf9-a025-2ba0be69bb48.jpg?aki_policy=x_medium","x_small":"https://a2.muscache.com/im/pictures/04937866-5885-4bf9-a025-2ba0be69bb48.jpg?aki_policy=x_small","xl_picture":"https://a2.muscache.com/im/pictures/04937866-5885-4bf9-a025-2ba0be69bb48.jpg?aki_policy=x_large","xx_large":"https://a2.muscache.com/im/pictures/04937866-5885-4bf9-a025-2ba0be69bb48.jpg?aki_policy=xx_large"},{"id":154311782,"picture":"https://a2.muscache.com/im/pictures/9061d985-293d-433f-9ac2-960d4a7051b9.jpg?aki_policy=large","sort_order":28,"caption":"","large":"https://a2.muscache.com/im/pictures/9061d985-293d-433f-9ac2-960d4a7051b9.jpg?aki_policy=large","large_cover":"https://a2.muscache.com/ac/pictures/9061d985-293d-433f-9ac2-960d4a7051b9.jpg?interpolation=lanczos-none&size=large_cover&output-format=jpg&output-quality=70","medium":"https://a2.muscache.com/im/pictures/9061d985-293d-433f-9ac2-960d4a7051b9.jpg?aki_policy=medium","mini_square":"https://a2.muscache.com/im/pictures/9061d985-293d-433f-9ac2-960d4a7051b9.jpg?aki_policy=mini_square","small":"https://a2.muscache.com/im/pictures/9061d985-293d-433f-9ac2-960d4a7051b9.jpg?aki_policy=small","thumbnail":"https://a2.muscache.com/im/pictures/9061d985-293d-433f-9ac2-960d4a7051b9.jpg?aki_policy=small","x_large":"https://a2.muscache.com/im/pictures/9061d985-293d-433f-9ac2-960d4a7051b9.jpg?aki_policy=x_large","x_large_cover":"https://a2.muscache.com/ac/pictures/9061d985-293d-433f-9ac2-960d4a7051b9.jpg?interpolation=lanczos-none&size=x_large_cover&output-format=jpg&output-quality=70","x_medium":"https://a2.muscache.com/im/pictures/9061d985-293d-433f-9ac2-960d4a7051b9.jpg?aki_policy=x_medium","x_small":"https://a2.muscache.com/im/pictures/9061d985-293d-433f-9ac2-960d4a7051b9.jpg?aki_policy=x_small","xl_picture":"https://a2.muscache.com/im/pictures/9061d985-293d-433f-9ac2-960d4a7051b9.jpg?aki_policy=x_large","xx_large":"https://a2.muscache.com/im/pictures/9061d985-293d-433f-9ac2-960d4a7051b9.jpg?aki_policy=xx_large"}],"picture_captions":["","","","","","","","","","","","","","","","","","","","","","","","","","","",""],"price_for_extra_person_native":50,"property_type_id":1,"public_address":"Oudezijds Voorburgwal, Amsterdam, Noord-Holland 1012 EH, Netherlands","require_guest_phone_verification":false,"requires_license":false,"security_deposit_formatted":"€500","security_deposit_native":500,"security_price_native":500,"space":"This district is thé place to be if you are in Amsterdam. The stunning Penthouse is amazing, centrally located, spacious and part of a monumental building. It’s an house of 150 square meters with 3 different levels and located in the heart of Amsterdam at the canal. If you would like to feel and live like a local of Amsterdam this is an amazing place to stay! The ultimate Amsterdam Experience. EVERYTHING WITHIN WALKING DISTANCE!\n\nStaying at this house will undoubtedly be a marvelous experience! This house is an amazing a true distinctive experience in the heart of Amsterdam. It’s an ideal loft on a perfect central location for yourself, family and friends to start to feel like a Local of Amsterdam at the same time, with an authentic and cultural atmosphere. This neighbourhood is brimming with great cafés, culinair restaurants, bars, galleries, museums, art&design, authentic shops. All that you need is there!\n\nBecause of the wonderful location of the apartment, you can really taste how it feels to live like a local of Amsterdam in the centre of the city. \n\nThis Traditional and Authentic Penthouse has got a huge characteristic living room where you can really relax after a day of exploring the city. There is a huge flat screen TV, some comfortable couches and chairs. On the other side of the apartment there is a fully equipped open kitchen with a lovely dining table and a breakfast bar. Perfect for a lovely dinner, breakfast, lunch or some wines and beers☺\nFrom the living you have an amazing view of oldest city centre of Amsterdam and it’s a great view spot for the canal. \n\nOn the top level of the penthouse\n‘The Eagle nest’, a very spacious Masterbedroom with a Kingsize Double bed, Flatscreen TV and enough storage space with next to it a big ensuite Masterbathroom and a separate toilet. \n\nOn the third floor; You will find 2 guestrooms with both double beds and enough storage space. Next to this rooms is also a separate study room/reading room with a desk, perfect for business or work. And a guest bathroom with a Rainshower and toilet.\n\nYou will also have access to free Wifi and enough storage space. Towels and linen are included for the whole period.\nAll of this in combination with the traditional house gives you a real experience of the historical ambiance of the Amsterdam! This house is perfect for a city trip, holiday or business trip you will never forget!\n\nWe are really looking forward to meet you, show you around at the apartment and to give you all the inside tips and tricks about Amsterdam. Please notice after 8pm we ask a late arrival fee of 20 euro and after 11pm 30 euro. \n\nIf you have got any questions please contact us!","square_feet":null,"star_rating":null,"summary":"Ever wanted to stay in Huge Penthouse in the Centre of Amsterdam at the canal?  This Penthouse is situated in the heart of Amsterdam near DAM square, Main station, Red Light district and close to Rembrandt square& the Nine Streets area.","time_zone_name":"Europe/Amsterdam","transit":"","weekly_price_factor":null,"weekly_price_native":null,"additional_house_rules":"YOU HAVE TO RESPECT THE NEIGHBOURS AND NEIGHBOURHOOD\nPLEASE TAKE CARE OF THE BELONGINGS!\nNO PARTIES","in_building":false,"in_toto_area":false,"recent_review":null,"toto_opt_in":null,"wireless_info":null,"listing_occupancy_info":{"show_occupancy_message":false},"review_rating_accuracy":null,"review_rating_checkin":null,"review_rating_cleanliness":null,"review_rating_communication":null,"review_rating_location":null,"review_rating_value":null,"is_business_travel_ready":false}}