{"metadata":{},"listing":{"city":"Amsterdam","collection_ids":null,"country":"Netherlands","has_double_blind_reviews":false,"id":4130891,"instant_bookable":false,"lat":52.36091317600015,"lng":4.905781283953371,"medium_url":"https://a0.muscache.com/im/pictures/51925645/aaf3837b_original.jpg?aki_policy=medium","name":"B&B Margareth Amsterdam","native_currency":"EUR","picture_url":"https://a0.muscache.com/im/pictures/51925645/aaf3837b_original.jpg?aki_policy=large","price":84,"price_formatted":"€75","price_native":75,"smart_location":"Amsterdam, Netherlands","thumbnail_url":"https://a0.muscache.com/im/pictures/51925645/aaf3837b_original.jpg?aki_policy=small","user":{"user":{"about":"","first_name":"Henk","has_profile_pic":true,"id":21431211,"identity_verified":false,"is_superhost":true,"picture_url":"https://a0.muscache.com/im/users/21431211/profile_pic/1410939182/original.jpg?aki_policy=profile_x_medium","reviewee_count":32,"thumbnail_url":"https://a0.muscache.com/im/users/21431211/profile_pic/1410939182/original.jpg?aki_policy=profile_small"}},"user_id":21431211,"xl_picture_url":"https://a0.muscache.com/im/pictures/51925645/aaf3837b_original.jpg?aki_policy=x_large","address":"Professor Tulpstraat, Amsterdam, North Holland 1018 GZ, Netherlands","bathrooms":1.0,"bedrooms":1,"beds":1,"cancellation_policy":"flexible","country_code":"NL","has_availability":true,"hosts":[{"about":"","first_name":"Henk","has_profile_pic":true,"id":21431211,"identity_verified":false,"is_superhost":true,"picture_url":"https://a0.muscache.com/im/users/21431211/profile_pic/1410939182/original.jpg?aki_policy=profile_x_medium","reviewee_count":32,"thumbnail_url":"https://a0.muscache.com/im/users/21431211/profile_pic/1410939182/original.jpg?aki_policy=profile_small"}],"listing_native_currency":"EUR","market":"Amsterdam","min_nights":2,"neighborhood":"Weesperbuurt en Plantage","person_capacity":2,"picture_count":8,"picture_urls":["https://a0.muscache.com/im/pictures/51925645/aaf3837b_original.jpg?aki_policy=large","https://a2.muscache.com/im/pictures/51925676/84a0260d_original.jpg?aki_policy=large","https://a1.muscache.com/im/pictures/51925704/dcdddc18_original.jpg?aki_policy=large","https://a0.muscache.com/im/pictures/51925728/17db098a_original.jpg?aki_policy=large","https://a2.muscache.com/im/pictures/51925748/610b4623_original.jpg?aki_policy=large","https://a1.muscache.com/im/pictures/51925811/ec4293d4_original.jpg?aki_policy=large","https://a2.muscache.com/im/pictures/54809077/0375003a_original.jpg?aki_policy=large","https://a2.muscache.com/im/pictures/54809111/1cb577cc_original.jpg?aki_policy=large"],"primary_host":{"about":"","first_name":"Henk","has_profile_pic":true,"id":21431211,"identity_verified":false,"is_superhost":true,"picture_url":"https://a0.muscache.com/im/users/21431211/profile_pic/1410939182/original.jpg?aki_policy=profile_x_medium","reviewee_count":32,"thumbnail_url":"https://a0.muscache.com/im/users/21431211/profile_pic/1410939182/original.jpg?aki_policy=profile_small"},"property_type":"Bed & Breakfast","reviews_count":32,"room_type":"Private room","room_type_category":"private_room","special_offer":null,"state":"North Holland","thumbnail_urls":["https://a0.muscache.com/im/pictures/51925645/aaf3837b_original.jpg?aki_policy=small","https://a2.muscache.com/im/pictures/51925676/84a0260d_original.jpg?aki_policy=small","https://a1.muscache.com/im/pictures/51925704/dcdddc18_original.jpg?aki_policy=small","https://a0.muscache.com/im/pictures/51925728/17db098a_original.jpg?aki_policy=small","https://a2.muscache.com/im/pictures/51925748/610b4623_original.jpg?aki_policy=small","https://a1.muscache.com/im/pictures/51925811/ec4293d4_original.jpg?aki_policy=small","https://a2.muscache.com/im/pictures/54809077/0375003a_original.jpg?aki_policy=small","https://a2.muscache.com/im/pictures/54809111/1cb577cc_original.jpg?aki_policy=small"],"xl_picture_urls":["https://a0.muscache.com/im/pictures/51925645/aaf3837b_original.jpg?aki_policy=x_large","https://a2.muscache.com/im/pictures/51925676/84a0260d_original.jpg?aki_policy=x_large","https://a1.muscache.com/im/pictures/51925704/dcdddc18_original.jpg?aki_policy=x_large","https://a0.muscache.com/im/pictures/51925728/17db098a_original.jpg?aki_policy=x_large","https://a2.muscache.com/im/pictures/51925748/610b4623_original.jpg?aki_policy=x_large","https://a1.muscache.com/im/pictures/51925811/ec4293d4_original.jpg?aki_policy=x_large","https://a2.muscache.com/im/pictures/54809077/0375003a_original.jpg?aki_policy=x_large","https://a2.muscache.com/im/pictures/54809111/1cb577cc_original.jpg?aki_policy=x_large"],"zipcode":"1018 GZ","bed_type":"Real Bed","bed_type_category":"real_bed","currency_symbol_left":"&euro;","force_mobile_legal_modal":true,"require_guest_profile_picture":false,"access":"You can use the balcony.\nLots of privacy which means that you have a private entrance from which you can receive a key on arrival.","amenities":["Internet","Wireless Internet","Buzzer/Wireless Intercom","Heating","Family/Kid Friendly","Smoke Detector","Carbon Monoxide Detector","First Aid Kit","Essentials","Shampoo","translation missing: en.hosting_amenity_49"],"amenities_ids":[3,4,28,30,31,35,36,37,40,41,49],"calendar_updated_at":"today","cancel_policy":3,"cancel_policy_short_str":"Flexible","check_in_time":12,"check_in_time_end":"NOT_SELECTED","check_in_time_ends_at":null,"check_in_time_start":"12","check_out_time":11,"cleaning_fee_native":null,"currency_symbol_right":null,"description":"Beautiful and spacious rooms in the center of Amsterdam near the Amstel Hotel.\nPlus Minus 1 minute walk tram and metro stop (Weesperplein). The subway is two stops to the Amstel and three stops to the Central Station.\nSights are within walking distance, for example (circus theater Carré, Skinny Bridge, Waterloo, Albert Cuyp market, etc.)\nNice shopping \"Utrechtsestraat\" is a 5 min walk away and ends at the Rembrandtplein. So as you sit in the middle of the city.\n\"the golden edge of town\"\n\nYou can use the balcony.\nLots of privacy which means that you have a private entrance from which you can receive a key on arrival.\n\nDo you wish HINTS activities you can make this known immediately or on the whiteboard in the hallway outside your room.","description_locale":"en","experiences_offered":"none","extra_user_info":null,"extras_price_native":null,"guests_included":2,"has_agreed_to_legal_terms":true,"has_license":false,"has_viewed_cleaning":null,"has_viewed_ib_perf_dashboard_panel":null,"has_viewed_terms":true,"house_rules":"Niet roken op kamer (evt. op balkon is daar gelegenheid voor)\nGeen drugs\nGeen Party’s","instant_book_welcome_message":null,"interaction":"Do you wish HINTS activities you can make this known immediately or on the whiteboard in the hallway outside your room.","is_location_exact":true,"jurisdiction_names":"Amsterdam","jurisdiction_rollout_names":"Amsterdam","language":"nl","license":null,"listing_cleaning_fee_native":null,"listing_monthly_price_native":null,"listing_price_for_extra_person_native":15,"listing_security_deposit_native":null,"listing_weekend_price_native":null,"listing_weekly_price_native":null,"locale":"nl","map_image_url":"https://maps.googleapis.com/maps/api/staticmap?maptype=roadmap&markers=52.36091317600015%2C4.905781283953371&size=480x320&zoom=15&client=gme-airbnbinc&channel=monorail-prod&signature=TPcFIn_P9XpIODxnKr1CkYOHBaQ%3D","max_nights":7,"max_nights_input_value":7,"min_nights_input_value":2,"monthly_price_factor":1.0,"monthly_price_native":null,"neighborhood_overview":"Bezienswaardigheden liggen op loopafstand b.v. (circustheater  Carré, Magere Brug, Waterlooplein, Albert Cuypmarkt enz.)\nLeuke winkelstraat “Utrechtsestraat”, is op 5 min. loopafstand en eindigd op het Rembrandtplein. Dus u zit zo in het midden van de stad.\nMen noemt de omgeving ook wel “het goude randje van de stad”","notes":"Voor het ontbijt, indien gewenst , dag van tevoren kenbaar maken tevens op het whiteboard. Kosten ontbijt € 8,50 per persoon.\nKosten voor 1 nacht boeking € 10,00 extra.","photos":[{"id":31737054,"picture":"https://a0.muscache.com/im/pictures/51925645/aaf3837b_original.jpg?aki_policy=large","sort_order":1,"caption":"","large":"https://a0.muscache.com/im/pictures/51925645/aaf3837b_original.jpg?aki_policy=large","large_cover":"https://a0.muscache.com/ac/pictures/51925645/aaf3837b_original.jpg?interpolation=lanczos-none&size=large_cover&output-format=jpg&output-quality=70","medium":"https://a0.muscache.com/im/pictures/51925645/aaf3837b_original.jpg?aki_policy=medium","mini_square":"https://a0.muscache.com/im/pictures/51925645/aaf3837b_original.jpg?aki_policy=mini_square","small":"https://a0.muscache.com/im/pictures/51925645/aaf3837b_original.jpg?aki_policy=small","thumbnail":"https://a0.muscache.com/im/pictures/51925645/aaf3837b_original.jpg?aki_policy=small","x_large":"https://a0.muscache.com/im/pictures/51925645/aaf3837b_original.jpg?aki_policy=x_large","x_large_cover":"https://a0.muscache.com/ac/pictures/51925645/aaf3837b_original.jpg?interpolation=lanczos-none&size=x_large_cover&output-format=jpg&output-quality=70","x_medium":"https://a0.muscache.com/im/pictures/51925645/aaf3837b_original.jpg?aki_policy=x_medium","x_small":"https://a0.muscache.com/im/pictures/51925645/aaf3837b_original.jpg?aki_policy=x_small","xl_picture":"https://a0.muscache.com/im/pictures/51925645/aaf3837b_original.jpg?aki_policy=x_large","xx_large":"https://a0.muscache.com/im/pictures/51925645/aaf3837b_original.jpg?aki_policy=xx_large"},{"id":31737055,"picture":"https://a2.muscache.com/im/pictures/51925676/84a0260d_original.jpg?aki_policy=large","sort_order":2,"caption":"","large":"https://a2.muscache.com/im/pictures/51925676/84a0260d_original.jpg?aki_policy=large","large_cover":"https://a2.muscache.com/ac/pictures/51925676/84a0260d_original.jpg?interpolation=lanczos-none&size=large_cover&output-format=jpg&output-quality=70","medium":"https://a2.muscache.com/im/pictures/51925676/84a0260d_original.jpg?aki_policy=medium","mini_square":"https://a2.muscache.com/im/pictures/51925676/84a0260d_original.jpg?aki_policy=mini_square","small":"https://a2.muscache.com/im/pictures/51925676/84a0260d_original.jpg?aki_policy=small","thumbnail":"https://a2.muscache.com/im/pictures/51925676/84a0260d_original.jpg?aki_policy=small","x_large":"https://a2.muscache.com/im/pictures/51925676/84a0260d_original.jpg?aki_policy=x_large","x_large_cover":"https://a2.muscache.com/ac/pictures/51925676/84a0260d_original.jpg?interpolation=lanczos-none&size=x_large_cover&output-format=jpg&output-quality=70","x_medium":"https://a2.muscache.com/im/pictures/51925676/84a0260d_original.jpg?aki_policy=x_medium","x_small":"https://a2.muscache.com/im/pictures/51925676/84a0260d_original.jpg?aki_policy=x_small","xl_picture":"https://a2.muscache.com/im/pictures/51925676/84a0260d_original.jpg?aki_policy=x_large","xx_large":"https://a2.muscache.com/im/pictures/51925676/84a0260d_original.jpg?aki_policy=xx_large"},{"id":31737056,"picture":"https://a1.muscache.com/im/pictures/51925704/dcdddc18_original.jpg?aki_policy=large","sort_order":3,"caption":"","large":"https://a1.muscache.com/im/pictures/51925704/dcdddc18_original.jpg?aki_policy=large","large_cover":"https://a1.muscache.com/ac/pictures/51925704/dcdddc18_original.jpg?interpolation=lanczos-none&size=large_cover&output-format=jpg&output-quality=70","medium":"https://a1.muscache.com/im/pictures/51925704/dcdddc18_original.jpg?aki_policy=medium","mini_square":"https://a1.muscache.com/im/pictures/51925704/dcdddc18_original.jpg?aki_policy=mini_square","small":"https://a1.muscache.com/im/pictures/51925704/dcdddc18_original.jpg?aki_policy=small","thumbnail":"https://a1.muscache.com/im/pictures/51925704/dcdddc18_original.jpg?aki_policy=small","x_large":"https://a1.muscache.com/im/pictures/51925704/dcdddc18_original.jpg?aki_policy=x_large","x_large_cover":"https://a1.muscache.com/ac/pictures/51925704/dcdddc18_original.jpg?interpolation=lanczos-none&size=x_large_cover&output-format=jpg&output-quality=70","x_medium":"https://a1.muscache.com/im/pictures/51925704/dcdddc18_original.jpg?aki_policy=x_medium","x_small":"https://a1.muscache.com/im/pictures/51925704/dcdddc18_original.jpg?aki_policy=x_small","xl_picture":"https://a1.muscache.com/im/pictures/51925704/dcdddc18_original.jpg?aki_policy=x_large","xx_large":"https://a1.muscache.com/im/pictures/51925704/dcdddc18_original.jpg?aki_policy=xx_large"},{"id":31737057,"picture":"https://a0.muscache.com/im/pictures/51925728/17db098a_original.jpg?aki_policy=large","sort_order":4,"caption":"","large":"https://a0.muscache.com/im/pictures/51925728/17db098a_original.jpg?aki_policy=large","large_cover":"https://a0.muscache.com/ac/pictures/51925728/17db098a_original.jpg?interpolation=lanczos-none&size=large_cover&output-format=jpg&output-quality=70","medium":"https://a0.muscache.com/im/pictures/51925728/17db098a_original.jpg?aki_policy=medium","mini_square":"https://a0.muscache.com/im/pictures/51925728/17db098a_original.jpg?aki_policy=mini_square","small":"https://a0.muscache.com/im/pictures/51925728/17db098a_original.jpg?aki_policy=small","thumbnail":"https://a0.muscache.com/im/pictures/51925728/17db098a_original.jpg?aki_policy=small","x_large":"https://a0.muscache.com/im/pictures/51925728/17db098a_original.jpg?aki_policy=x_large","x_large_cover":"https://a0.muscache.com/ac/pictures/51925728/17db098a_original.jpg?interpolation=lanczos-none&size=x_large_cover&output-format=jpg&output-quality=70","x_medium":"https://a0.muscache.com/im/pictures/51925728/17db098a_original.jpg?aki_policy=x_medium","x_small":"https://a0.muscache.com/im/pictures/51925728/17db098a_original.jpg?aki_policy=x_small","xl_picture":"https://a0.muscache.com/im/pictures/51925728/17db098a_original.jpg?aki_policy=x_large","xx_large":"https://a0.muscache.com/im/pictures/51925728/17db098a_original.jpg?aki_policy=xx_large"},{"id":31737058,"picture":"https://a2.muscache.com/im/pictures/51925748/610b4623_original.jpg?aki_policy=large","sort_order":5,"caption":"","large":"https://a2.muscache.com/im/pictures/51925748/610b4623_original.jpg?aki_policy=large","large_cover":"https://a2.muscache.com/ac/pictures/51925748/610b4623_original.jpg?interpolation=lanczos-none&size=large_cover&output-format=jpg&output-quality=70","medium":"https://a2.muscache.com/im/pictures/51925748/610b4623_original.jpg?aki_policy=medium","mini_square":"https://a2.muscache.com/im/pictures/51925748/610b4623_original.jpg?aki_policy=mini_square","small":"https://a2.muscache.com/im/pictures/51925748/610b4623_original.jpg?aki_policy=small","thumbnail":"https://a2.muscache.com/im/pictures/51925748/610b4623_original.jpg?aki_policy=small","x_large":"https://a2.muscache.com/im/pictures/51925748/610b4623_original.jpg?aki_policy=x_large","x_large_cover":"https://a2.muscache.com/ac/pictures/51925748/610b4623_original.jpg?interpolation=lanczos-none&size=x_large_cover&output-format=jpg&output-quality=70","x_medium":"https://a2.muscache.com/im/pictures/51925748/610b4623_original.jpg?aki_policy=x_medium","x_small":"https://a2.muscache.com/im/pictures/51925748/610b4623_original.jpg?aki_policy=x_small","xl_picture":"https://a2.muscache.com/im/pictures/51925748/610b4623_original.jpg?aki_policy=x_large","xx_large":"https://a2.muscache.com/im/pictures/51925748/610b4623_original.jpg?aki_policy=xx_large"},{"id":31737059,"picture":"https://a1.muscache.com/im/pictures/51925811/ec4293d4_original.jpg?aki_policy=large","sort_order":6,"caption":"","large":"https://a1.muscache.com/im/pictures/51925811/ec4293d4_original.jpg?aki_policy=large","large_cover":"https://a1.muscache.com/ac/pictures/51925811/ec4293d4_original.jpg?interpolation=lanczos-none&size=large_cover&output-format=jpg&output-quality=70","medium":"https://a1.muscache.com/im/pictures/51925811/ec4293d4_original.jpg?aki_policy=medium","mini_square":"https://a1.muscache.com/im/pictures/51925811/ec4293d4_original.jpg?aki_policy=mini_square","small":"https://a1.muscache.com/im/pictures/51925811/ec4293d4_original.jpg?aki_policy=small","thumbnail":"https://a1.muscache.com/im/pictures/51925811/ec4293d4_original.jpg?aki_policy=small","x_large":"https://a1.muscache.com/im/pictures/51925811/ec4293d4_original.jpg?aki_policy=x_large","x_large_cover":"https://a1.muscache.com/ac/pictures/51925811/ec4293d4_original.jpg?interpolation=lanczos-none&size=x_large_cover&output-format=jpg&output-quality=70","x_medium":"https://a1.muscache.com/im/pictures/51925811/ec4293d4_original.jpg?aki_policy=x_medium","x_small":"https://a1.muscache.com/im/pictures/51925811/ec4293d4_original.jpg?aki_policy=x_small","xl_picture":"https://a1.muscache.com/im/pictures/51925811/ec4293d4_original.jpg?aki_policy=x_large","xx_large":"https://a1.muscache.com/im/pictures/51925811/ec4293d4_original.jpg?aki_policy=xx_large"},{"id":31737060,"picture":"https://a2.muscache.com/im/pictures/54809077/0375003a_original.jpg?aki_policy=large","sort_order":7,"caption":"","large":"https://a2.muscache.com/im/pictures/54809077/0375003a_original.jpg?aki_policy=large","large_cover":"https://a2.muscache.com/ac/pictures/54809077/0375003a_original.jpg?interpolation=lanczos-none&size=large_cover&output-format=jpg&output-quality=70","medium":"https://a2.muscache.com/im/pictures/54809077/0375003a_original.jpg?aki_policy=medium","mini_square":"https://a2.muscache.com/im/pictures/54809077/0375003a_original.jpg?aki_policy=mini_square","small":"https://a2.muscache.com/im/pictures/54809077/0375003a_original.jpg?aki_policy=small","thumbnail":"https://a2.muscache.com/im/pictures/54809077/0375003a_original.jpg?aki_policy=small","x_large":"https://a2.muscache.com/im/pictures/54809077/0375003a_original.jpg?aki_policy=x_large","x_large_cover":"https://a2.muscache.com/ac/pictures/54809077/0375003a_original.jpg?interpolation=lanczos-none&size=x_large_cover&output-format=jpg&output-quality=70","x_medium":"https://a2.muscache.com/im/pictures/54809077/0375003a_original.jpg?aki_policy=x_medium","x_small":"https://a2.muscache.com/im/pictures/54809077/0375003a_original.jpg?aki_policy=x_small","xl_picture":"https://a2.muscache.com/im/pictures/54809077/0375003a_original.jpg?aki_policy=x_large","xx_large":"https://a2.muscache.com/im/pictures/54809077/0375003a_original.jpg?aki_policy=xx_large"},{"id":31737061,"picture":"https://a2.muscache.com/im/pictures/54809111/1cb577cc_original.jpg?aki_policy=large","sort_order":8,"caption":"","large":"https://a2.muscache.com/im/pictures/54809111/1cb577cc_original.jpg?aki_policy=large","large_cover":"https://a2.muscache.com/ac/pictures/54809111/1cb577cc_original.jpg?interpolation=lanczos-none&size=large_cover&output-format=jpg&output-quality=70","medium":"https://a2.muscache.com/im/pictures/54809111/1cb577cc_original.jpg?aki_policy=medium","mini_square":"https://a2.muscache.com/im/pictures/54809111/1cb577cc_original.jpg?aki_policy=mini_square","small":"https://a2.muscache.com/im/pictures/54809111/1cb577cc_original.jpg?aki_policy=small","thumbnail":"https://a2.muscache.com/im/pictures/54809111/1cb577cc_original.jpg?aki_policy=small","x_large":"https://a2.muscache.com/im/pictures/54809111/1cb577cc_original.jpg?aki_policy=x_large","x_large_cover":"https://a2.muscache.com/ac/pictures/54809111/1cb577cc_original.jpg?interpolation=lanczos-none&size=x_large_cover&output-format=jpg&output-quality=70","x_medium":"https://a2.muscache.com/im/pictures/54809111/1cb577cc_original.jpg?aki_policy=x_medium","x_small":"https://a2.muscache.com/im/pictures/54809111/1cb577cc_original.jpg?aki_policy=x_small","xl_picture":"https://a2.muscache.com/im/pictures/54809111/1cb577cc_original.jpg?aki_policy=x_large","xx_large":"https://a2.muscache.com/im/pictures/54809111/1cb577cc_original.jpg?aki_policy=xx_large"}],"picture_captions":["","","","","","","",""],"price_for_extra_person_native":15,"property_type_id":3,"public_address":"Professor Tulpstraat, Amsterdam, North Holland 1018 GZ, Netherlands","require_guest_phone_verification":false,"requires_license":false,"security_deposit_formatted":"","security_deposit_native":null,"security_price_native":null,"space":"","square_feet":null,"star_rating":4.5,"summary":"Beautiful and spacious rooms in the center of Amsterdam near the Amstel Hotel.\nPlus Minus 1 minute walk tram and metro stop (Weesperplein). The subway is two stops to the Amstel and three stops to the Central Station.\nSights are within walking distance, for example (circus theater Carré, Skinny Bridge, Waterloo, Albert Cuyp market, etc.)\nNice shopping \"Utrechtsestraat\" is a 5 min walk away and ends at the Rembrandtplein. So as you sit in the middle of the city.\n\"the golden edge of town\"","time_zone_name":"Europe/Amsterdam","transit":"Plusminus 1 minuut loopafstand tram en metro halte (Weesperplein). Met de metro is het twee stops naar het Amstelstation en drie stops naar het Centralstation.","weekly_price_factor":1.0,"weekly_price_native":null,"additional_house_rules":"Niet roken op kamer (evt. op balkon is daar gelegenheid voor)\nGeen drugs\nGeen Party’s","in_building":false,"in_toto_area":false,"recent_review":{"review":{"comments":"This was our first experience using airbnb. And it was a great experience. Henk and Margret were so helpful even did our washing. Nothing was too much trouble. The room was well laid out and most importantly for me was extremely clean. It is a 15 to 20minute walk to city centre with so many little shops, restaurants etc along the way. If  walking is a problem for you the metro is about 2minutes and tram also. We only used metro when arriving and leaving because of or suitcases. There is no tv but thats not what we came to Amsterdam for anyway.We loved this place and definately recommend it.","created_at":"2016-06-03T03:57:02Z","id":77699913,"listing_id":4130891,"reviewee_id":21431211,"reviewer":{"user":{"first_name":"Diane","has_profile_pic":true,"id":51051770,"picture_url":"https://a2.muscache.com/im/pictures/9f896555-ef7b-4af4-9d9d-80f940eca510.jpg?aki_policy=profile_x_medium","thumbnail_url":"https://a2.muscache.com/im/pictures/9f896555-ef7b-4af4-9d9d-80f940eca510.jpg?aki_policy=profile_small"}},"reviewer_id":51051770,"role":"guest"}},"toto_opt_in":null,"wireless_info":null,"listing_occupancy_info":{"show_occupancy_message":true},"review_rating_accuracy":10,"review_rating_checkin":10,"review_rating_cleanliness":10,"review_rating_communication":10,"review_rating_location":10,"review_rating_value":10,"is_business_travel_ready":false}}